{
  "不良/極差": "-50",
  "重/差": "0",
  "稍重/稍差": "0",
  "良/良好": "0",
  "練習上手": "擅長練習",
  "愛嬌": "討人喜歡",
  "注目株": "備受矚目",
  "切れ者": "天賦異凜",
  "夜ふかし気味": "睡眠不足",
  "練習ベタ": "不擅長練習",
  "なまけ癖": "懶惰成性",
  "太り気味": "體重過胖",
  "片頭痛": "偏頭痛",
  "肌あれ": "膚況不好",
  "小さなほころび": "微小的裂痕",
  "大輪の輝き": "燦爛的光芒",
  "凸凹ネイル": "立體美甲",
  "大逃げ": "強勢領頭",
  "日本一のウマ娘": "日本第一的賽馬娘",
  "食の極意": "飲食的祕訣",
  "いつまでも健やかに": "願永遠健康",
  "私たちの走る道程": "我們走上的旅程",
  "アスリート魂": "運動員之魂",
  "バーニングソウル": "燃燒靈魂",
  "爆熱のキラメキ！": "熾烈的閃耀光輝！",
  "想いを背負って": "背負意志",
  "最高峰の夢": "最高峰之夢",
  "陽の加護": "太陽的庇護",
  "太陽の叡智": "太陽的睿智",
  "海の加護": "大海的庇護",
  "大海の叡智": "大地的睿智",
  "地の加護": "大地的庇護",
  "前だけ見据えて": "只注視前方",
  "限界の先へ": "超越極限",
  "レースの真髄・速": "競賽的精髓．速度",
  "レースの真髄・体": "競賽的精髓．體能",
  "レースの真髄・力": "競賽的精髓．力量",
  "レースの真髄・根": "競賽的精髓．意志",
  "レースの真髄・賢": "競賽的精髓．智慧",
  "レースの真髄・心": "競賽的精髓．心得",
  "夢の途中": "夢想的途中",
  "キミと勝ちたい想和你一起獲得勝利": "想和你一起獲得勝利",
  "綺羅星": "璀璨繁星",
  "一番星": "一等星",
  "アオハル点火・速": "青春點火・速度",
  "アオハル燃焼・速": "青春燃燒・速度",
  "アオハル点火・体": "青春點火・體能",
  "アオハル燃焼・体": "青春燃燒・體能",
  "アオハル点火・力": "青春點火・力量",
  "アオハル燃焼・力": "青春燃燒・力量",
  "アオハル点火・根": "青春點火・意志",
  "アオハル燃焼・根": "青春燃燒・意志",
  "アオハル点火・賢": "青春點火・智慧",
  "アオハル燃焼・賢": "青春燃燒・智慧",
  "逃げコーナー/": "領頭彎道/",
  "陣風円刃": "陣風圓刃",
  "先行コーナー/": "前列彎道/",
  "差しコーナー/": "居中彎道/",
  "鋭脚円刃": "銳腳圓刃",
  "追込コーナー/": "後追彎道/",
  "月影円刃": "月影圓刃",
  "短距離コーナー/": "短距離彎道/",
  "紫電円刃": "紫電圓刃",
  "マイルコーナー/": "一哩彎道/",
  "豪風円刃": "豪風圓刃",
  "中距離コーナー/": "中距離彎道/",
  "光芒円刃": "光芒圓刃",
  "長距離コーナー/": "長距離彎道/",
  "ダートコーナー/": "沙地彎道/",
  "逃げ直線/": "領頭直線/",
  "陣風一閃": "陣風一閃",
  "先行直線/": "前列直線/",
  "差し直線/": "居中直線/",
  "鋭脚一閃": "銳腳一閃",
  "追込直線/": "後追直線/",
  "月影一閃": "月影一閃",
  "短距離直線/": "短距離直線/",
  "紫電一閃": "紫電一閃",
  "マイル直線/": "一哩直線/",
  "豪風一閃": "豪風一閃",
  "中距離直線/": "中距離直線/",
  "光芒一閃": "光芒一閃",
  "長距離直線/": "長距離直線/",
  "烈風一閃": "烈風一閃",
  "ダート直線/": "沙地直線/",
  "登山家": "登山家",
  "究極のヒルクライマー": "終極攀坡者",
  "下り坂巧者": "下坡靈巧",
  "至高のダウンヒラー": "至高的下坡強者",
  "あやしげな作戦": "可疑的作戰",
  "博打うち": "好賭之徒",
  "ウマ好み": "喜愛賽馬娘",
  "ウママニア": "賽馬娘狂粉",
  "地固め": "打好基礎",
  "盤石の構え": "磐石的架式",
  "尻尾上がり": "豎起尾巴",
  "尻尾の滝登り": "尾巴躍龍門",
  "スリップストリーム": "滑流",
  "いいとこ入った！": "搶到好位置了！",
  "遊びはおしまいっ！": "遊戲到此為止了!",
  "お先に失礼っ！": "我先失陪！",
  "コーナー巧者×": "彎道靈巧×",
  "コーナー巧者": "彎道靈巧",
  "弧線のプロフェッサー": "弧線的教授",
  "コーナー加速×": "彎道加速×",
  "コーナー加速": "彎道加速",
  "曲線のソムリエ": "曲線的侍酒師",
  "直線巧者": "直線靈巧",
  "ハヤテ一文字": "疾風一文字",
  "直線加速": "直線加速",
  "一陣の風": "快如陣風",
  "末脚": "尾段加速",
  "全身全霊": "全心全力",
  "ペースアップ": "加速步調",
  "アガッてきた！": "追上去！",
  "快速": "快速",
  "神速": "神速",
  "折れない心": "堅毅之心",
  "ネバーギブアップ": "永不放棄",
  "中盤巧者": "中期靈巧",
  "時中の妙": "絕佳良機",
  "序盤巧者": "初期靈巧",
  "機先の勝負": "洞察機先的對決",
  "集中力": "集中力",
  "コンセントレーション": "全神貫注",
  "ポジションセンス": "取位天賦",
  "注目の踊り子": "矚目的舞者",
  "臨機応変": "臨機應變",
  "レーンの魔術師": "跑道的魔術師",
  "垂れウマ回避": "避開力竭賽馬娘",
  "ノンストップガール": "不停頓女孩",
  "素直な一歩": "率直的一步",
  "正攻法": "正攻法",
  "危険回避": "迴避危險",
  "シックスセンス": "第六感",
  "先駆け": "先鋒",
  "先手必勝": "先發必勝",
  "急ぎ足": "疾行",
  "脱出術": "逃脫術",
  "押し切り準備": "準備強行衝線",
  "逃亡者": "逃亡者",
  "先頭プライド": "領先的自尊",
  "トップランナー": "頂尖跑者",
  "二の矢": "第二對策",
  "再燃焼": "再次燃燒",
  "しゃかりき": "孜孜不倦",
  "出力1000％！": "1000％輸出！",
  "粘り腰": "堅定不移",
  "踏ませぬ影": "遙不可及的影子",
  "抜け出し準備": "準備突圍",
  "スピードスター": "速度之星",
  "まき直し": "重整態勢",
  "くじけぬ精神": "不屈不撓",
  "巧みなステップ": "靈巧步伐",
  "技巧派": "技巧派",
  "直滑降": "直線滑下",
  "決意の直滑降": "決心的直線滑下",
  "真っ向勝負": "正面對決",
  "鍔迫り合い": "短兵相接",
  "攻めの姿勢": "進攻的姿態",
  "アンストッパブル": "勢不可擋",
  "向上心": "上進心",
  "風雲の志": "風雲之志",
  "食らいつき": "咬住不放",
  "猛追": "猛追",
  "会心の一歩": "自信的一步",
  "王手": "將軍",
  "勝利に向かって": "邁向勝利",
  "かっとばせ！": "轟出去吧！",
  "飛躍の予感": "飛躍的預感",
  "流星光底": "流星一瞬",
  "決定打": "決勝一擊",
  "幕引き": "落幕",
  "十万バリキ": "十萬衝勁",
  "百万バリキ": "百萬衝勁",
  "位置取り押し上げ": "前驅取位",
  "迅速果断": "迅速果斷",
  "外差し準備": "準備外側超前",
  "昇り龍": "昇龍",
  "がんばり屋": "努力不懈",
  "努力家": "奮發圖強",
  "差し切り体勢": "居中超前姿勢",
  "乗り換え上手": "熟練轉換",
  "読解力": "解讀力",
  "大局観": "大局觀",
  "フルスロットル": "氣閥全開",
  "勇往邁進": "勇往直前",
  "恐れぬ心": "無畏之心",
  "大胆不敵": "大膽無畏",
  "がむしゃら": "不顧一切",
  "無我夢中": "渾然忘我",
  "キレる脚": "迅猛之腳",
  "トップギア": "最高檔速",
  "プレッシャー": "壓力",
  "威風堂々": "威風凜凜",
  "進出開始": "開始推進",
  "突撃魂": "突擊魂",
  "溢れる情熱": "滿溢的熱情",
  "一歩から": "始於足下",
  "千里の道": "千里之行",
  "むきだしの情熱": "毫無保留的熱情",
  "本能の解放": "解放本能",
  "直線一気": "直線一口氣",
  "迫る影": "逼近的身影",
  "仕掛け抜群": "進攻時機超群",
  "疾風怒濤": "疾風怒濤",
  "お見通し": "看穿",
  "視界良好！異常なし！！": "視線良好！沒有異狀！",
  "策士": "策士",
  "天命士": "天命士",
  "早仕掛け": "提前進攻",
  "強攻策": "強攻計策",
  "打開策": "突圍計策",
  "ブレイクスルー": "突破",
  "切れ味": "衝勁",
  "抜群の切れ味": "過人的衝勁",
  "推力十分": "推力十足",
  "飛翔脚": "飛翔腳",
  "たぎる血潮": "沸騰血潮",
  "惜しみなし": "毫無保留",
  "一心不乱": "一心不亂",
  "影踏み": "踏影而行",
  "手練手管": "玩弄指掌",
  "掌握": "掌握",
  "スプリントギア": "短途檔位",
  "スプリントターボ": "短途渦輪",
  "大きなリード": "大幅領先",
  "圧倒的リード": "壓倒性領先",
  "善後策": "善後策略",
  "プランX": "X計劃",
  "仕掛け準備": "準備進攻",
  "準備万全！": "準備萬全！",
  "軽い足取り": "腳步輕盈",
  "意気衝天": "意氣昂揚",
  "詰め寄り": "窮追不捨",
  "電撃の煌めき": "電擊光輝",
  "一足飛び": "一飛衝天",
  "電光石火": "電光石火",
  "ひたむき前進": "專注前進",
  "気骨稜稜": "堅守信念",
  "急発進": "急速起步",
  "ロケットスタート": "火箭起跑",
  "胸の高鳴り": "激昂的內心",
  "トキメキハート": "心動不已",
  "瞬発力": "瞬間爆發力",
  "電迅速攻": "迅雷速攻",
  "無二": "無二",
  "無三": "無三",
  "積極策": "積極應對",
  "マイルの支配者": "一哩支配者",
  "ギアシフト": "變速",
  "ギアチェンジ": "換檔",
  "アクセラレーション": "加速度",
  "アクセル全開！": "油門全開！",
  "負けん気": "不服輸",
  "姉御肌": "姐姐氣質",
  "上昇気流": "上昇氣流",
  "豪脚": "強勁腳力",
  "気合十分": "氣勢十足",
  "破竹の勢い": "勢如破竹",
  "向こう見ず": "不顧後果",
  "遮二無二": "義無反顧",
  "心弾んで": "雀躍",
  "ハイボルテージ": "熱情澎湃",
  "品行方正": "品行端正",
  "十全十美": "十全十美",
  "滾る想い": "激揚的意志",
  "熱情": "熱情",
  "風切り": "破風",
  "風翔": "御風",
  "テンポアップ": "加快節奏",
  "キラーチューン": "致勝曲調",
  "食い下がり": "緊咬不放",
  "勝利への執念": "對勝利的執著",
  "ホークアイ": "鷹眼",
  "千里眼": "千里眼",
  "イナズマステップ": ">閃電步伐",
  "ライトニングステップ": "閃光步伐",
  "ありったけ": "傾注一切",
  "決死の覚悟": "必死的決心",
  "前のめり": "積極前進",
  "高揚感": "興奮感",
  "闘争心": "鬥爭心",
  "気炎万丈": "氣勢如虹",
  "ワンチャンス": "機不可失",
  "起死回生": "起死回生",
  "気迫を込めて": "灌注氣魄",
  "荒ぶる旋風": "狂野旋風",
  "イグニッション": "點火",
  "ルミネセンス": "冷性發光",
  "一番乗り": "搶得先機",
  "誰より前へ！": "比誰都前方！",
  "確かな足取り": "穩健的步伐",
  "快進撃": "過關斬將",
  "型破り": "破格",
  "天衣無縫": "天衣無縫",
  "しとやかな足取り優雅的步伐": "優雅的步伐",
  "優位形成": "形成優勢",
  "込み上げる熱": "湧現熱量",
  "昂る鼓動": "激昂的心跳",
  "渾身の足取り": "全力以赴的步伐",
  "君臨": "君臨",
  "鬼気迫って": "鬼氣逼人",
  "揺るがぬ信念": "堅定的信念",
  "初志貫徹": "貫徹初衷",
  "正面突破": "正面突破",
  "王道一途": "王道征途",
  "さらなる高みへ": "邁向更高的境界",
  "強者の証": "強者的證明",
  "克己心": "克己之心",
  "怜悧清澄": "伶俐剔透",
  "リードキープ": "維持領先",
  "先陣の心得": "前鋒的心得",
  "内弁慶": "內側強者",
  "内的体験": "內在體驗",
  "追い上げ": "後來居上",
  "怒涛の追い上げ": "怒濤的後來居上",
  "影打": "暖場好戲",
  "真打": "壓軸好戲",
  "ロックオン": "鎖定",
  "一発必中": "一發必中",
  "本領発揮": "發揮本領",
  "怪物": "怪物",
  "大急ぎ": "匆促",
  "一気呵成": "一氣呵成",
  "バイブス上昇": "心情上升",
  "ブチアゲ↑バイブス": "超嗨↑心情",
  "狙いを定めて": "瞄準目標",
  "大詰め": "終幕",
  "画竜点睛": "畫龍點睛",
  "迷いなし": "無所迷惘",
  "万里一空": "水滴石穿萬里行",
  "ごぼう抜き": "脫穎而出",
  "一網打尽": "一網打盡",
  "好機を捉えて": "緊抓良機",
  "レコメンド": "精選推薦",
  "チャート急上昇！": "排行驟升！",
  "前列狙い": "鎖定前排",
  "狙うは最前列！": "目標是最前排！",
  "明るい兆し": "明朗之兆",
  "勝利の機運": "勝利的機運",
  "盛り返し": "重振旗鼓",
  "捲土重来": "捲土重來",
  "まっしぐら": "長驅直入",
  "全速前進！": "全速前進！",
  "冴える思考思緒清晰": "思緒清晰",
  "明鏡止水": "明鏡止水",
  "砂浴び/✕": "砂浴び/✕",
  "優雅な砂浴び": "優雅地沙浴",
  "意気込み十分": "熱情十足",
  "目指せセンター！": "目標是中央站位！",
  "急浮上": "緊急上升",
  "爆走モード！": "爆走模式！",
  "二段構え": "未雨綢繆",
  "コール&レスポンス": "打call&回應",
  "パイオニア": "先驅者",
  "砂の開拓者": "沙地的開拓者",
  "力の限り": "竭盡全力",
  "踏みしめる大地": "腳踏大地",
  "ふり絞り": "使盡全力",
  "スリーセブン": "777",
  "直線回復": "直線回復",
  "好転一息": "好轉歇息",
  "コーナー回復×": "彎道回復×",
  "コーナー回復": "彎道回復",
  "円弧のマエストロ": "圓弧的藝術家",
  "隠れ蓑": ">隱藏身影",
  "鋼の意志": "鋼鐵意志",
  "ウマ込み冷静": "混戰冷靜",
  "どこ吹く風": "充耳不聞",
  "ペースキープ": "維持步調",
  "不屈の心": "不屈之心",
  "勢い任せ": "隨勢而動",
  "じゃじゃウマ娘": "強悍賽馬娘",
  "スタミナキープ": "維持持久力",
  "余裕綽々": "綽綽有餘",
  "栄養補給": "補充營養",
  "食いしん坊": "貪吃鬼",
  "好位追走": "好位追趕",
  "レースプランナー": "賽場規劃師",
  "小休憩": "稍微休息",
  "リラックス": "放鬆",
  "静かな呼吸": "沉靜的呼吸",
  "潜伏態勢": "潜伏態勢",
  "後方待機": "後方待機",
  "眠れる獅子": "沉睡的獅子",
  "下校の楽しみ": "放學的樂趣",
  "下校後のスペシャリスト": "放學後的專家",
  "冷静": "冷靜",
  "冷静沈着": "沉著冷靜",
  "不動の心": "不動之心",
  "様子見": "靜觀其變",
  "展開窺い": "觀察情勢",
  "慧眼": "慧眼",
  "軽やかステップ": "輕快步伐",
  "神業ステップ": "神技步伐",
  "前途洋々": "前途無量",
  "切り開く者": "突破者",
  "パス上手": "熟練超越",
  "VIP顔パス": "VIP常客",
  "深呼吸": "深呼吸",
  "クールダウン": "冷卻",
  "別腹タンク": "第二體力條",
  "火事場のバ鹿力": "腎上腺素爆發",
  "マイペース": "我行我素",
  "泰然自若": "泰然自若",
  "抜かりなし": "毫無破綻",
  "一意専心": "專心致志",
  "脇目も振らず": "心無旁鶩",
  "脱兎の先へ": "脫兔的彼端",
  "砂塵慣れ": "適應沙塵",
  "砂の玄人": "沙之行家",
  "砂払い": "除去沙塵",
  "砂の妙手": "沙地妙手",
  "良バ場//✕": "良好場地//✕",
  "良バ場の鬼": "良好場地之鬼",
  "道悪//✕": "路況差勁//✕",
  "道悪の鬼": "路況差勁之鬼",
  "晴れの日//✕": "晴天//✕",
  "曇りの日//✕": "陰天//✕",
  "雨の日//✕": "下雨天//✕",
  "雪の日//✕": "下雪天//✕",
  "根幹距離//✕": "主要距離//✕",
  "非根幹距離//✕": "非主要距離//✕",
  "逃げのコツ/": "領頭的訣竅/",
  "先行のコツ/": "前列的訣竅/",
  "差しのコツ/": "居中的訣竅/",
  "追込のコツ/": "後追的訣竅/",
  "東京レース場//✕": "東京賽場//✕",
  "府中の申し子": "府中奇才",
  "中山レース場//✕": "中山賽場//✕",
  "阪神レース場//✕": "阪神賽場//✕",
  "京都レース場//✕": "京都賽場//✕",
  "淀の申し子": "淀之奇才",
  "中京レース場//✕": "中京賽場//✕",
  "札幌レース場//✕": "札幌賽場//✕",
  "函館レース場//✕": "函館賽場//✕",
  "福島レース場//✕": "福島賽場//✕",
  "新潟レース場//✕": "新潟賽場//✕",
  "小倉レース場//✕": "小倉賽場//✕",
  "大井レース場//✕": "大井賽場//✕大井賽場",
  "川崎レース場//✕": "川崎賽場//✕",
  "盛岡レース場//✕": "盛岡賽場//✕",
  "船橋レース場//✕": "船橋賽場//✕",
  "ロンシャンレース場//✕": "隆尚賽場//✕",
  "ロンシャンの申し子": "隆尚奇才",
  "対抗意識//引っ込み思案": "對抗意識//內向保守",
  "内枠得意//内枠苦手": "擅長內側閘位//不擅長內側閘位",
  "外枠得意//外枠苦手": "擅長外側閘位//不擅長外側閘位",
  "伏兵/": "伏兵/",
  "右回り//✕": "順時針//✕",
  "右回りの鬼": "順時針之鬼",
  "左回り//✕": "逆時針//✕",
  "徹底マーク/": "徹底鎖定/",
  "春ウマ娘//✕": "春賽馬娘//✕",
  "春一番": "春初暖風",
  "夏ウマ娘//✕": "夏賽馬娘//✕",
  "青嵐": "青嵐",
  "秋ウマ娘//✕": "秋賽馬娘//✕",
  "初嵐": "秋初強風",
  "冬ウマ娘//✕": "冬季賽馬娘//✕",
  "凍て風": "冷冽之風",
  "ラッキーセブン": "幸運7",
  "スーパーラッキーセブン": "超級幸運7",
  "シンパシー": "同理心",
  "一匹狼": "獨行俠",
  "おひとり様/": "喜歡獨處/",
  "自制心": "自制心",
  "交流重賞//✕": "交流主要競賽//✕",
  "ナイター//✕": "夜間賽//✕",
  "小回り//✕": "急彎り//✕",
  "踏み込み上手": "熟練邁步",
  "抜群の踏み込み": "超群的邁步",
  "泥遊び//✕": "玩泥巴び//✕",
  "泥んこマイスター": "泥巴大師",
  "やまっけ": "投機取巧",
  "勝負師": "賭徒",
  "自信家": "自信家",
  "雲蒸竜変": "虎嘯風生",
  "探求心": "探求心",
  "シンギュラリティ奇異點": "シンギュラリティ奇異點",
  "直線コース//✕": "直線賽道//✕",
  "トリック": "謀略",
  "見惚れるトリック": "吸睛謀略",
  "逃げけん制": "牽制領頭",
  "先行けん制": "牽制前列",
  "差しけん制": "牽制居中",
  "追込けん制": "牽制後追",
  "逃げ駆け引き": "對領頭策略",
  "先行駆け引き": "對前列策略",
  "差し駆け引き": "對居中策略",
  "追込駆け引き": "對後追策略",
  "逃げ焦り": "使領頭焦躁",
  "先行焦り": "使前列焦躁",
  "差し焦り": "使居中焦躁",
  "追込焦り": "使後追焦躁",
  "逃げためらい": "使領頭遲疑",
  "先行ためらい": "使前列遲疑",
  "差しためらい": "使居中遲疑",
  "追込ためらい": "使後追遲疑",
  "リスタート": "重新開始",
  "かく乱": "干擾",
  "幻惑のかく乱": "幻覺干擾",
  "鋭い眼光": "銳利眼光",
  "八方にらみ": "緊盯八方",
  "まなざし": "凝視",
  "熱いまなざし": "熱情凝視",
  "後方釘付": "緊盯後方",
  "悩殺術": "魅惑術",
  "抜け駆け禁止": "禁止搶先",
  "逃亡禁止令": "逃亡禁令",
  "布石": ">布局",
  "布陣": "布陣",
  "スピードイーター": "速度吞噬者",
  "スピードグリード": "速度貪食者",
  "ささやき": "細語",
  "魅惑のささやき": "魅惑的細語",
  "束縛": "束縛",
  "独占力": "獨佔力",
  "スタミナイーター": "持久力吞噬者",
  "スタミナグリード": "持久力貪食者",
  "目くらまし": "障眼法",
  "奇術師": "奇術師",
  "土煙": "塵煙",
  "砂上の舞姫": "沙上的舞姬",
  "圧迫感": "壓迫感",
  "油断大敵": "大意失荊州",
  "小心者": "膽小",
  "ゲート難": "閘門障礙",
  "バ群嫌い": "討厭成群",
  "G1苦手": "不擅長G1",
  "坂苦手": "不擅長上坡",
  "あきらめ癖": "習慣放棄",
  "手抜き癖": "習慣偷懶",
  "空回り": "空轉",
  "U.A.F.模式": "燃えてきたッ！！",
  "ベストを尽くして！": "マイル或中距離+最後衝刺前半路程=速+45001.U.A.F大會總合全部為優勝",
  "ステイチューン！": "中距離+比賽中段+前名次=速+45001.擁有最少2項中距離限定技能2.U.A.F大會總合全部為優勝",
  "繋がる高揚感": "中距離+比賽中段+或之後名次=速+45001.擁有最少2項中距離限定技能2.U.A.F大會總合全部為優勝",
  "破竹の筋肉": "マイル+最後彎位+或之後名次=速+45001.擁有最少2項マイル限定技能2.U.A.F大會總合全部為優勝",
  "無二の情熱": "マイル+比賽中段後半+前名次=速+45001.擁有最少2項マイル限定技能2.U.A.F大會總合全部為優勝",
  "キラメキの勝負": "マイル或中距離+比賽早段後半=速+45001.U.A.F大會總合全部為優勝",
  "大豊食祭模式": "曲線のグランシェフ",
  "耕せ！開墾スプリント": "短距離或マイル+比賽終段=加速力+4000,發動後續最後200m內=速+15001.大豊食祭模式全部料理チャレンジ為大満足",
  "即席三ツ星コーナリング": "短距離或マイル+彎位=速+45001.擁有最少2項短距離限定技能2.大豊食祭模式全部料理チャレンジ為大満足",
  "ここらで味変！": "短距離或マイル+比賽中段=速+45001.大豊食祭模式全部料理チャレンジ為大満足",
  "お待ちどおさま！": "短距離或マイル+比賽終段+後半名次+有追越目標=加速力+4000,發動後續最後200m內=速+15001.擁有最少2項短距離限定技能,或擁有最少2項マイル限定技能2.大豊食祭模式全部料理チャレンジ為大満足",
  "敬愛ッ！ウママニア": "短距離或マイル+附近1.5身位內有3位或以上的馬娘=速+45001.大豊食祭模式全部料理チャレンジ為大満足",
  "メカウマ娘模式": "モンスターマシン",
  "リカバリーシーケンス": "現在速+1500→2500,無限定→限定中距離或長距離",
  "システムオールグリーン": "速+2500→3500",
  "リミッター解除": "速+3500→4500,無限定→限定中距離或長距離",
  "先頭維持アルゴリズム": "速+3500→4500",
  "弧線のトップスカラー": "速+3500→4500,無限定→限定中距離或長距離",
  "TheTwinkleLegends模式": "伝説降臨",
  "疾風より先へ": "速+3500→4500",
  "革命の岐路": "速+3500→4500",
  "夢の先駆者": "發動技能後額外於最後衝刺前半路程現在速+1500",
  "幾星霜が導く一手": "發動技能後額外於最後直路現在速+1500",
  "雲上飛翔": "發動技能後額外於最後衝刺中間路程現在速+1500",
  "無人島模式": "開拓者の軌跡",
  "未知へのトライアル": "速+2500→3500",
  "不屈のサバイバル魂": "發動技能額外最後直路現在速+1500,無限定→限定中距離或長距離",
  "大地を揺るがす疾走": "速+3500→4500,無限定→限定中距離或長距離",
  "ワイルドアットハート": "速+3500→4500",
  "大自然の鼓動": "速+3500→4500",
  "溫泉鄉模式": "一番風呂いただきます！",
  "走り湯ダッシュ": "速+3500→4500",
  "湯に入りて湯に入らざれ": "速+3500→4500",
  "秘湯より湧くチカラ": "持續時間2.4秒→4秒,無限定→限定差し或追込",
  "噴泉スピリット": "速+3500→4500",
  "ゴールドシップ黃金船": "VivelaGOLD",
  "不沈艦、抜錨ォッ！不沉艦起錨！": "於比賽中段大幅上前1.比賽路程2.後半名次=速+2500/繼承速+500",
  "564アイズで視界クッキリ！/564之眼讓視野清晰！": "額外回+1501.育成事件「いざ、真剣勝負！」選擇下方並成功,或擁有最少2項回持久力技能2.スタミナ600+",
  "エクストリーム下校術/極限放學術": "額外速+15001.發生育成事件「気まぐれオトメのゴルシちゃん」並進行訓練,或擁有最少2項追込限定技能2.長距離G12勝",
  "ウオッカ伏特加": "IntoHighGear!",
  "カッティング×DRIVE！CUTTING×DRIVE！": "最後200m與其他馬娘並排時速度上升1.最後200m2.第3至一半名次3.與前方或後方馬娘1身位內=速+3500/繼承速+1500",
  "スキットルブレイク/酒瓶歇息": "額外速+15001.勝出日本ダービー,或スピード800+2.擁有最少3項提升速度的技能",
  "抜群の豪脚/超群的強勁腳力": "加速力4000→50001.勝出阪神JF、安田記念,或擁有最少2項マイル限定技能2.パワー800+",
  "ダイワスカーレット大和赤驥": "Queen'sLumination",
  "ブリリアント・レッドエース燦爛．赤色王牌": "比賽後半段保持領先/搶奪領先位置1.超過一半路程2.第1名名次3.領先1身位內；或1.超過一半路程2.第2名位置3.超越第1名馬娘=速+2500,加速力+3000/繼承速+500,加速力+1000",
  "パーフェクトチューン/完美曲調": "額外回+1501.勝出桜花賞、オークス、秋華賞,或中距離G12勝2.擁有最少2項中距離限定技能",
  "アタシが勝つんだから！/贏的人是我！": "額外速+15001.6次在重賞取得前2名2.スピード800+",
  "グラスワンダー草上飛": "演舞・撫子大薙刀",
  "精神一到何事か成らざらん精誠所至金石為開": "最後直路追越前方馬娘時速度上升1.最後直路2.第3名或之後名次3.追越馬娘=速+3500/繼承速+1500",
  "大和撫子": "技能改動:1.比賽終段前半=速+45001.スピード800+2.擁有最少3項提升速度的技能",
  "不退転の意思/堅定不移的意志": "額外視野+51.勝出1場マイル/一哩路程G12.勝出1場中距離路程G1",
  "エルコンドルパサー神鷹": "コンドル猛撃波兀鷹猛擊波",
  "プランチャガナドール勝利者飛身撲": "最後直路仍有餘力時保持優勢1.最後直路2.耐力餘值大於3.前2名名次=速+2500,加速力+3000/繼承速+500,加速力+1000",
  "鷹ノ目/鷹眼": "額外速+15001.勝出最少3場中距離G12.スピード800+",
  "余裕のパフォーマンス/游刃有餘的表現": "額外視野+51.重賞5次前2名2.擁有最少2項先行限定技能",
  "エアグルーヴ氣槽": "薫風、永遠なる瞬間を暖風吹向永恆的瞬間",
  "ブレイズ・オブ・プライド自尊之炎": "最後彎位之後從後追越時速度上升1.最後彎位至終點2.第3名或之後名次3.追越馬娘=速+3500/繼承速+1500",
  "女帝の権謀/女帝的權謀": "技能改動:1.先行2.比賽終段前半3.前半名次=速+35001.勝出オークス,或擁有最少3項提升速度技能2.擁有最少2項先行限定技能",
  "水月鏡花/鏡花水月": "額外現在速+15001.スピード800+,或パワー800+2.擁有最少2項提升加速力技能",
  "マヤノトップガン重砲": "HOPSTEP♪LOCKON!",
  "ひらめきランディング閃耀著陸": "在最後彎位之後於前方與其他馬娘並排時更容易於最後直路佔先1.最後彎位至終點2.前3名名次3.與其他馬娘並排2秒=速+2500,加速力+3000/繼承速+500,加速力+1000",
  "Youcopy?": "回550→7501.擁有最少4項中距離限定技能,或擁有最少4項長距離限定技能",
  "Icopy!": "額外回+1501.勝出第2年有馬記念,或勝出最少3場G12.擁有最少2項回復持久力技能",
  "メジロライアン目白雷恩": "あなたに捧げるフリーポア獻給你的拉花",
  "レッツ・アナボリック！合成代謝開始！": "比賽終段彎位嘗試佔領前方位置時加速力上升1.比賽終段的最後彎位2.後3名次=加速力+4000/繼承加速力+2000",
  "マッスルアンセム/肌肉讚歌": "速3500→45001.勝出最少2場中距離重賞2.ファン数150000+",
  "ライジングバルクアップ/急速增肌": "速3500→45001.育成事件「筋肉に不可能は……！？」大成功,或パワー800+2.擁有最少2項差し限定技能",
  "アグネスタキオン愛麗速子": "超光速微粒子の可能性",
  "U=ma2": "比賽後半彎位控制良好時回復更多耐力1.比賽後半+彎位2.第3至前名次=回+550,速+2500/繼承回+150,速+500",
  "可能性の徒/可能性之徒": "技能改動:1.中距離2.比賽終段前半1.擁有最少4項中距離限定技能,或擁有最少5項提升速度技能",
  "効率的休息法/高效休息法": "額外速+15001.勝出ホープフルS,或スピード800+2.擁有最少2項先行限定技能",
  "ウイニングチケット勝利獎券": "GO！Full-send",
  "勝利のチケットを、君にッ！將勝利的獎券獻給你！": "最後彎位之後於前方與其他馬娘並排,於最後直路速度上升1.最後彎位至終點+與其他馬娘並排2秒2.最後直路為前5名名次=速+3500/繼承速+1500",
  "たゆまぬ努力/努力不懈": "額外速+15001.勝出日本ダービー,或パワー800+2.擁有最少3項提升速度技能",
  "ウイニングロード/勝利之路": "速3500→45001.スタミナ600+,或ファン数150000+2.擁有最少2項回復持久力技能",
  "サクラバクシンオー櫻花驀進王": "CHERRYスクランブル",
  "優等生×バクシン=大勝利ッ模範生×驀進＝大獲全勝": "比賽後半於前方與其他馬娘並排時速度上升1.比賽後半2.前3名名次3.與其他馬娘並排2秒=速+3500/繼承速+1500",
  "バクシン的スプリント/驀進式的短途賽！": "額外速+15001.勝出第2,3年スプリンターズS,或擁有最少5項提升速度技能",
  "バクシン的リード！/驀進式的領先！": "速3500→45001.曾發生育成事件「学級委員長の、名に懸けて！」,或スピード800+2.曾發生育成事件「いざ、委員長勝負！！」,或賢さ800+",
  "スーパークリーク超級小溪": "忍法・ほほえみ心結の印",
  "ピュリティオブハート/療癒的藝術家純潔之心": "比賽中段處位良好位置時回復更多耐力1.比賽中段2.第2至前名次=回+繼承回+350",
  "あま~い幻惑/甜~蜜的幻覺": "技能改動:1.先行2.比賽終段前半3.前半名次=速+35001.育成事件「夜の甘い誘惑」選擇最上方,或賢さ800+2.擁有最少2項先行限定技能",
  "癒しのマエストロ": "回550→7501.勝出最少3場長距離G12.擁有最少4項回復持久力技能",
  "ハルウララ春烏菈菈": "113転び114起き113跌倒114爬起",
  "ワクワククライマックス雀躍不已的精彩時刻": "最後彎位在其他馬娘隔壁時回復更多耐力1.最後彎位或之後2.後半名次3.附近有馬娘=回+繼承回+150",
  "まだまだだよ！/還能繼續跑喔！": "回550→7501.持有「愛嬌〇」狀態完成育成,或擁有最少2項轉換跑線技能2.ファン数150000+",
  "まけないからね！/一定不會輸的！": "額外速+15001.根性600+2.擁有最少3項提升速度技能+",
  "マチカネフクキタル待兼福來": "禾スナハチ登ル三候秋收開始",
  "来ます来てます来させます！顯靈了顯靈了請顯靈吧！": "比終段受阻時開路1.比賽終段2.第3或之後名次3.受阻=速+3500,加速+1000/繼承速+1500,加速+500",
  "吉兆です！": "技能改動:1.長距離2.比賽終段前半=速+35001.勝出2項長距離限定技能2.スタミナ600+",
  "七福即生": "速+60,耐+60,力+60→速+80,耐+80,力+80,附合條件必定觸發1.勝出函館記念,或擁有最少3項提升速度技能2.勝出小倉記念,或擁有最少2項提升加速力技能",
  "ナイスネイチャ優秀素質": "もちっと・ハレハレQ彈．陽光普照",
  "きっとその先へ…！一定能抵達前方…！": "比賽終段處於第3名時速度上升1.比賽終段2.第3名名次3.與其他馬娘1身位內=速+3500/繼承速+1500",
  "魅惑のシニカルガール/魅惑的語中帶刺女孩": "技能改動:1.中距離2.比賽終段3.受阻1秒=加速力+40001.曾在比賽得第3名,或擁有最少2項中距離限定技能2.曾發生育成事件「スルメ、いかがです？」,或擁有最少2項提升加速力技能",
  "目指せ！主人公！/目標是！主角！": "技能改動:1.差し2.比賽終段前半=速+35001.曾在比賽得第3名,或擁有最少2項差し限定技能2.曾發生育成事件「スルメ、いかがです？」,或擁有最少3項提升速度技能",
  "キングヘイロー帝王光輝": "理想へのwindingroad",
  "PrideofKING": "在比賽中保持冷靜,最後200m速度上升1.沒有出現掛かり2.最後200m3.第4至前名次=速+4500/繼承速+2500",
  "電撃の撫で切り/電擊橫掃": "持續時間3秒→4秒1.勝岀5場G12.擁有最少2項短距離限定技能",
  "王の大局観/王的大局觀": "額外速+15001.勝岀5場G12.擁有最少3項提升速度技能",
  "スペシャルウィーク特別週": "威風堂々、夢錦！威風凜凜,揭夢！",
  "はらぺこ大将/飢腸轆轆的大將": "額外速+15001.スタミナ600+2.3+速度上升技能",
  "夢叶える末脚/實現夢想的尾段加速": "速+3500→速+45001.勝出ジャパンC2.G12勝+3.賢さ800+",
  "サイレンススズカ無聲鈴鹿": "水平線のその先へ邁向水平線的彼端",
  "最大集中": "額外加速力+20001.勝出宝塚記念,或以逃げ作戰勝出最少2場G22.スピード800+",
  "異次元の逃亡者": "額外即時速+15001.擁有「大逃げ」2.擁有最少4項「逃げ」限定技能",
  "トウカイテイオー東海帝皇": "歌舞歓楽や、ああをかし歌舞昇平,趣味橫生",
  "天才的技巧": "加速力3000→4000,額外速+25001.勝出皐月賞、日本ダービー,或ファン数150000+2.スピード800+",
  "帝王ステップ/帝王舞步": "額外速+25001.擁有最少2項有「コース取/轉換跑線」效果的技能2.擁有最少3項提升速度的技能",
  "マルゼンスキー丸善斯基": "霊験灼然チョベリグ神託",
  "かっ飛ばすわよ！/要全力衝刺囉！": "速+3500→速+45001.勝出朝日杯FS,或擁有項マイル限定技能2.スピード800+",
  "紅蓮のオーバーレブ/紅蓮的超速運轉": "技能改動:1.マイル2.一半路程3.第1名名次=速+45001.G14勝或以上",
  "レッドゾーンを突き抜けて": "技能改動:1.マイル2.比賽終段3.有追越目標1秒=速+3500曾發生事件「マルゼンスキー、『好き』を語る」,或賢さ800+2.勝出最少2場マイル重賞",
  "オグリキャップ小栗帽": "灰の光跡：シンデレラグレイ",
  "笠松の食いしん坊/笠松的貪吃鬼": "回+550→7501.育成事件「オグリの大食い選手権」選擇最下方「食って食って……全てを食い尽くせ！」,或有馬記念二連霸",
  "飢えた怪物": "回+550→150,速+35001.G14勝,或擁有最少5項提升速度技能",
  "怪物的コーナリング/如怪物般的過彎": "額外回+1501.勝出マイルCS、安田記念,或勝出短距離賽2.ファン数150000+",
  "タイキシャトル大樹快車": "HaveS'moreLove!",
  "狙い撃ちデス！/瞄準射擊喔！": "速+3500→45001.パワー800+2.擁有最少2項先行限定技能",
  "FrontierSpirit": "速+3500→45001.マイルCS二連霸,或勝出最少3場マイルG12.擁有最少2項マイル限定技能",
  "メジロマックイーン目白麥昆": "きらめくは海、まばゆきは君波光粼粼的海,燦爛輝煌的你",
  "メジロの心得/目白的心得": "技能改動:1.長距離2.比賽中段3.前名次=速+45001.勝出菊花賞,或ファン数150000+2.擁有最少2項長距離限定技能",
  "名優の余裕/名演員的餘裕": "額外速+15001.育成事件「レース場グルメの誘惑」選擇最下方「むしろお腹いっぱい食べよう！」,或スタミナ600+2.擁有最少2項先行限定技能",
  "シンボリルドルフ魯道夫象徵": "翳り退く、さざめきの矢劃破陰霾之響箭",
  "皇帝の眼差し/皇帝的眼神": "技能改動:1.中距離2.比賽終段前半=速+45001.育成事件「いついかなる時も」「突然の厚意」「有言実行」其中一個選擇上方選項,或ファン数150000+2.擁有最少2項中距離限定技能",
  "陰りなき王道": "技能改動:1.長距離2.比賽終段3.追越對手=現在速+3500,加速力+20001.發生最少3次提升やる気的育成事件,或勝出最少2場長距離G12.擁有最少2項長距離限定技能",
  "鎧袖一触/技壓群雄": "持續時間2.4秒→4秒1.勝出皐月賞、日本ダービー、菊花賞,或擁有最少3項提升速度技能2.スタミナ600+,或賢さ800+",
  "ライスシャワー米浴": "あおぞらクッキング♪",
  "決意のヒーロー/決心的英雄": "額外現在速+15001.根性600+2.ファン数150000+",
  "黒の刺客/黑色刺客": "額外速+15001.勝出菊花賞,或擁有最少2項長距離限定技能2.擁有最少3項提升速度技能",
  "テイエムオペラオー好歌劇": "恵福バルカローレ惠福的船歌",
  "降臨！世紀末覇王！/降臨！世紀末霸王！": "持續時間1.8秒→4秒1.有出現育成事件「鏡よ、鏡」,或ファン数150000+2.擁有最少2項先行限定技能",
  "歌劇王の行進/歌劇王的行進": "速+3500→45001.勝出最少2場中距離G12.擁有最少2項中距離限定技能",
  "ミホノブルボン美浦波旁": "オペレーション・Cacao巧克力作戰行動",
  "クロックアップ/超頻": "加速力4000→50001.勝出日本ダービー,或勝出最少2場G12.擁有最少2項提升加速力技能",
  "困難を乗り越える者/跨越困難之人": "額外速+15001.育成事件「鬼トレーニング」選擇上方並成功,或スタミナ600+2.擁有最少3項提升速度技能",
  "ビワハヤヒデ琵琶晨光": "勝利ヘ至ル累積",
  "想定通り、余裕十分/符合預期,餘力十足": "回550→7501.勝出菊花賞,或賢さ800+2.擁有最少2項回復持久力技能",
  "計画的クールダウン/計畫性冷卻": "回550→7501.勝出天皇賞,或5次在重賞得前2名2.擁有最少2項長距離限定技能",
  "レースの天才/競賽的天才": "額外速+15001.勝出天皇賞,或勝出兩場長距離重賞2.スタミナ600+",
  "地平の彼方まで/直到地平線的另一端": "額外速+15001.擁有最少2項有「コース取/轉換跑線」效果的技能2.勝出兩場中距離重賞",
  "アクティブレスト/積極休養": "額外速+15001.勝出最少2場長距離重賞2.擁有最少2項長距離限定技能",
  "空の果てまで/直衝天際": "速+3500→45001.スピード800+2.擁有最少3項提升速度技能",
  "カレンチャン真機伶": "OneTrueColor",
  "＃カワイイかく乱♪/#可愛的干擾♪": "額外現在速+15001.勝出函館スプリントS,或パワー800+2.勝出キーンランドC,或擁有2先行限定技能",
  "＃夢中になっちゃえ♪/#對我如痴如醉吧♪": "額外速+15001.持有「愛嬌〇」狀態完成育成,或ファン数150000+2.勝出最少3場G1",
  "ナリタタイシン成田大進": "OverdriveSpeed",
  "鬼気森然/鬼氣森然": "額外速+15001.擁有最少4項追込限定技能,或擁有最少5項提升速度技能",
  "駆り立てる想い/難以壓抑的意志": "額額外視野+51.勝出天皇賞,或勝出最少3場G12.根性600+",
  "スマートファルコン醒目飛鷹": "ForWardMarch!",
  "大注目のウマドル参上/超受矚目的賽馬娘偶像登場": "持續時間3秒→4秒1.完成育成事件「ConnectLive~それから~」,或勝出7場ダートG1",
  "目を逸らしちゃダメだよ/賽馬娘偶像之力驟升↑↑": "技能更改:比賽終段=現在速+25001.持有「愛嬌」狀態完成育成,或ファン数150000+2.スピード800+,或パワー800+",
  "ウマドルパワー急上昇↑↑": "額外回+1501.スピード800+,或擁有最少2項ダート限定技能2.擁有最少2項回復持久力技能",
  "ナリタブライアン成田白仁": "灰色の臨界点灰色臨界點",
  "一刀両断/一刀兩斷": "速+3500→45001.勝出皐月賞、日本ダービー、菊花賞,或スピード800+2.擁有最少3項提升速度的技能",
  "餓狼牙": "速+3500→45001.育成事件「岐」選擇上方「強豪たちとの戦いを望み『出席する』」,或ファン数150000+2.スタミナ600+",
  "女帝の矜持/女帝的矜持": "持續時間2.4秒→4秒1.勝出最少2場マイルG1,或ファン数150000+2.擁有最少2項マイル限定技能",
  "上弦のソムリエール/上弦的侍酒師": "額外現在速+15001.持有「愛嬌〇」狀態完成育成,或パワー800+2.擁有最少2項提升加速力技能",
  "未来へ続く放物線": "無限定→限定マイル,加速力4000→3000,芝比賽時額外現在速+25001.スピー800+2.根性600+",
  "純白のささやき/純白的細語": "額外速+15001.勝出最少2場中距離G12.スピード800+",
  "バレルロール/桶滾": "回550→7501.持有「切れ者」狀態完成育成,或スタミナ600+2.擁有最少2項中距離限定技能,或擁有最少2項長距離限定技能",
  "セイウンスカイ青雲天空": "DoYaBreakin!",
  "ファストリトリーブ/快速捲線": "持續時間3秒→4秒1.勝出菊花賞,或勝出最少3場長距離G12.擁有最少2項長距離限定技能,或曾中「なまけ癖」",
  "大物狙いの心得": "技能變更:比賽中段回+750,限定中距離1.育成事件「晴天の攻防」點選中間,或スタミナ600+2.擁有最少2項中距離限定技能",
  "脱出大作戦/逃脫大作戰": "持續時間3秒→4秒1.スタミナ600+,或賢さ800+2.擁有最少2項逃げ限定技能",
  "ヒシアマゾン菱亞馬遜": "大盛り！ファーストバイト！",
  "勝利への咆哮/通往勝利的咆哮": "速+3500→4500,被追越→追越1.勝出阪神JF、秋華賞,或パワー800+2.擁有最少2項中距離限定技能",
  "タイマンにかける執念": "速+3500→4500,加速力+1000→0,被追越→追越,最後200m發動1.勝出秋華賞,或根性600+2.擁有最少3項提升速度技能",
  "怒濤のポロロッカ/怒濤的湧潮": "速+3500→45001.以追込作戰勝出6場重賞",
  "豪勇無双/豪勇無雙": "加速力4000→50001.勝出每日王冠,或勝出最少2場マイル重賞2.擁有最少2項マイル限定技能",
  "コンドル跳躍術/昇龍兀鷹": "技能變更:マイル+比賽終段=現在速+35001.勝出NHKマイルC,スピード800+2.根性600+",
  "昇りコンドル": "持續時間3秒→4秒1.以差し作戰勝出最少2場重賞2.擁有最少2項差し限定技能",
  "キュアリーヒール/完全治癒術": "額外速+15001.擁有最少4項回復持久力技能,或擁有最少3項提升速度的技能2.スタミナ600+",
  "勇気の魔法/勇氣的魔法": "額外速+15001.以差し作戰勝出最少2場G1,或擁有最少2項長距離限定技能2.賢さ800+",
  "フジキセキ富士奇石": "Ravissant",
  "輝くトップスタァ/閃耀的頂尖巨星": "速+3500→速+45001.勝出マイルCS,或擁有最少2項マイル限定技能2.ファン数150000+",
  "エンターテイナー/娛樂表演者": "額外速+15001.出戰菊花賞,或擁有最少2項先行限定技能2.スピード800+",
  "煌めくキセキを": "回+550→150,速+35001.パワー800+,或擁有最少3項提升速度技能2.賢さ800+",
  "ゴールドシチー黃金城市": "SilentSunsetGold",
  "先見の明/先見之明": "額外速+25001.曾發生育成事件「寝坊した……！」,或根性600+2.擁有最少3項提升速度技能",
  "ランウェイの主役/伸展台的主角": "額外視野+51.曾發生育成事件「モデルのお仕事」,或勝出最少2場G12.擁有最少2項差し限定技能",
  "フィナーレの先頭へ": "發動技能後額外最後200m速+15001.ファン数150000+,或擁有最少2項提升加速力技能2.パワー800+",
  "真夏の思い切り/竭盡全力的盛夏": "技能持續時間2.4秒→4秒1.以差し作戰勝出兩場重賞2.スタミナ600+",
  "真夏の総大将/盛夏的總大將": "技能持續時間2.4秒→4秒1.勝出日本ダービー2.勝出兩場中距離重賞3.パワー800+",
  "ドキッじゃじゃウマ娘！/心動強悍賽馬娘！": "回+550→回+7501.勝出日本ダービー,或以逃げ作戰勝山兩場G22.賢さ800+",
  "渚の激マブウマ娘": "逃げ→逃げ+マイル,回+550→+150,現在速+35001.スピード800+2.擁有最少2項逃げ限定技能",
  "お立ち台の支配者/站台的支配者": "速+3500→速+45001.勝出兩場マイル路程重賞2.擁有最少2項マイル限定技能",
  "メイショウドトウ名將怒濤": "Spooky-Scary-Happy",
  "怒涛のスピード/怒濤的速度": "持續時間1.8秒→4秒1.勝出天皇賞、ジャパンC,或スタミナ600+2.擁有最少2項先行限定技能",
  "諦めない、ですぅ~！/我不會、放棄的~！": "額外速+15001.曾發生育成事件「目覚めの先で」,或擁有最少5項提升速度技能",
  "エイシンフラッシュ榮進閃耀": "潮風のGeschenk",
  "閃光のマギア/閃光的魔法": "額外現在速+25001.育成事件「試験:フラッシュプラン」選擇上方,或擁有最少2項轉換跑線技能2.擁有最少2項提升加速力技能",
  "誇りを懸けて/賭上榮耀": "速+3500→速+45001.勝出最少3場東京賽場比賽,或賢さ800+2.擁有最少3項提升速度技能",
  "怒涛の超幸運パワー！怒涛の追い上げ": "維持時間3秒→4秒1.曾與育成角色外出,或與友人卡或團體卡外出2.擁有最少2項長距離限定技能",
  "怒涛のラッキー大猛進！怒涛の追い上げ": "速+3500,加速力+1000→加速力+2000,發外額外於最後衝刺有追越目標時速+35001.スタミナ600+2.根性600+",
  "ばっちり開運体験！": "維持時間3秒→4秒1.曾與育成角色外出,或與友人卡或團體卡外出2.賢さ800+",
  "ヒシアケボノ菱曙": "シュガーパレード･始動！",
  "下ごしらえ万全！/事前準備萬無一失！": "額外速+15001.勝出最少4場G12.擁有最少2項短距離限定技能",
  "ボーノな健啖/Buono的大食客家": "額外速+15001.育成事件「お夜食ちゃんこの効能」選擇上方選項,或パワー800+2.擁有最少3項提升速度技能",
  "はっけよい！": "技能改動:短距離+比賽中段=速+5500,回-2001.育成事件「お夜食ちゃんこの効能」選擇上方選項,或パワー800+2.擁有最少3項提升速度技能",
  "アグネスデジタル愛麗數碼": "萌到讓我活過來了！",
  "限界ウママニア/極限賽馬娘狂粉": "額外回+1501.勝出最少2場芝G1,或勝出最少2場ダートG12.擁有最少3項提升速度技能",
  "最前列は譲れない！/絕不讓出最前排！": "持續時間3秒→4秒1.スピード800+,或スタミナ800+2.パワー800+,或賢さ800+",
  "狙うは最前ドセンへの道！": "技能更改:中距離+比賽終段,ダート=現在速+2500,芝=現在速+30001.勝出最少2場中距離G1,或スピード800+2.擁有最少2項中距離限定技能",
  "がんばるぞー…おー！/要加油囉……哦──！": "額外速+15001.スタミナ600+,或パワー800+2.擁有最少3項提升速度技能",
  "トリック&トリート/要糖也要搗蛋": "額外速+35001.勝出最少2場京都賽場比賽2.スピード800+",
  "お世話のプロフェッショナル/照顧人的專業人士": "額外回+1501.勝出最少3場G1,或スピード800+2.スタミナ600+,或賢さ800+",
  "魅惑のマミーウィスパー/魅惑的木乃伊細語": "額外回+1501.育成事件「夜の甘い誘惑」選擇最下方,或擁有最少2項中距離限定技能2.擁冇項回復持久力技能",
  "カワカミプリンセス川上公主": "快なる剛力",
  "ノンストッププリンセス/不停頓公主": "加速力4000→50001.勝出オークス,或根性600+2.勝出秋華賞,或パワー800+",
  "暴れ龍/狂暴之龍": "額外加速力+20001.育成事件「完成！究極フォーム！」選擇上方並成功,或擁有差し限定技能",
  "マンハッタンカフェ曼哈頓咖啡": "心からのおもてにゃし由衷的喵情款待",
  "コーヒーブレイク/咖啡小歇": "額外速+15001.勝出最少2場長距離重賞2.擁有最少3項提升速度技能",
  "オイテイカナイデ/不要丟下我": "額外速+15001.擁有最少4項回復持久力技能,或擁有最少4項長距離限定技能",
  "神色自若/神色自若": "回550→7501.勝出ジャパンC,或勝出最少2場中距離G12.擁有最少2項先行限定技能",
  "風霜高潔": "速+60,力+60→速+80,力+801.スピード800+,或パワー800+2.擁有最少2項綠技",
  "鮮やかな布陣/艷麗的布陣": "額外回+1501.賢さ800+,或擁有最少2項マイル限定技能2.擁有最少2項回復持久力技能",
  "虎視眈々/虎視眈眈": "額外速+15001.曾發生育成事件「寝坊した……！」,或勝出最少2場G12.擁有最少3項提升速度技能",
  "トーセンジョーダン島川喬登": "ヤバ技ジャグルビート",
  "ノってこ！/一起嗨！": "額外回+1501.根性600+2.擁有最少2項先行限定技能,或擁有最少2項差し限定技能",
  "トレンドプランナー/潮流規劃師": "額外速+15001.有馬記念二連霸,或勝出最少2場G12.擁有最少2項先行限定技能,或擁有最少2項差し限定技能",
  "メジロドーベル目白多伯": "ときめきが呼ぶほうへ奔向讓人心動之處",
  "クールな視線/冷酷的視線": "額外回+1501.出戰天皇賞,或賢さ800+2.擁有最少2項提升加速力技能",
  "栄光への羽ばたき": "差し+比賽終段=現在速+35001.以差し作戰勝出最少4場中距離G1",
  "淀の女王/淀之女王": "耐+60,智+60,速+60→耐+80,智+80,速+801.勝出最少2場京都賽場比賽2.擁有最少2項綠技",
  "VIPな後ろ姿/VIP的背影": "回550→7501.勝出最少3場G12.擁有最少2項回復持久力技能",
  "全力サンタクロース/全力以赴的聖誕老人": "速3500→45001.パワー800+2.スタミナ600+",
  "ドカ食い養生/暴飲暴食養生": "回+550→回+7501.育成事件「オグリの大食い選手権」選擇最下方「食って食って……全てを食い尽くせ！」,或育成期間曾中「太り気味」2.擁有最少2項回復持久力技能",
  "クリスマスの奇跡体験/聖誕的奇蹟體驗": "額外回+1501.有馬記念二連霸,或スピード800+2.ファン数150000+",
  "ファインモーション美妙姿勢": "Bestdayever",
  "ロイヤルスター/皇家之星": "額外回+1501.曾發生「MoreFun!」育成事件,或擁有最少3項提升速度技能2.擁有最少2項先行限定技能",
  "ディライトフルメモリー": "先行→先行+中距離,速+3500→現在速+35001.曾發生最少3次やる気上升育成事件,或賢さ800+2.擁有最少2項中距離限定技能",
  "天空落とし/天墜": "加速力+3000→40001.勝出エリザベス女王杯,或パワー800+2.擁有最少2項提升加速力技能",
  "タマモクロス玉藻十字": "火神鳴",
  "雷騰雲奔": "速+3500→45001.持有「切れ者」狀態完成育成,或パワー800+2.賢さ800+",
  "ちゃちゃっと始めんで！": "速+3500→2500,回+3501.長距離G12勝2.スピード800+",
  "尻尾の有頂天/忘乎所以的尾巴": "速+3500→25001.持有「切れ者」狀態完成育成,或スタミナ600+2.勝出天皇賞",
  "円舞曲のマエストロ/圓舞曲的藝術家": "回550→7501.育成事件「激走・福ウマ娘レース！」成功,或スタミナ600+2.擁有最少2項回復持久力技能",
  "コーナーに舞い降りし歌劇王": "技能更改:長距離+比賽中段+彎位=速+3500,回+1501.勝出最少2場長距離G12.ファン数150000+",
  "ボクは遅れずにやってくる！/我會在最佳時機登場！": "速+3500→45001.勝出最少2場長距離G12.スピード800+",
  "見てて見てて！/看好囉看好囉！": "額外速+15001.持有「愛嬌〇」狀態完成育成,或勝出10場ダート/沙地比賽2.擁有最少2項回復持久力技能",
  "勝ちたいんだもん！/我會繼續努力嘛！": "技能改動:比賽終段=轉換跑線+450,加速力+30001.ファン数150000+2.根性600+",
  "がんばるもん！": "額外速+15001.パワー800+2.擁有最少3項提升速度技能+",
  "サクラチヨノオー櫻花千代王": "咲け咲け！私！盛開吧盛開吧！我！",
  "お花見当たり年！/賞花當及時！": "持續時間1.8秒→4秒1.勝出ジャパンC,或擁有最少5項提升速度技能",
  "案ずるより走るが速し": "速+3500→45001.擁有最少2項先行限定技能,或擁有最少2項中距離限定技能2.スピード800+",
  "けふ九重に満開です/今日九重宮中櫻花盛開": "速+60,力+60→速+80,力+801.勝出皐月賞、日本ダービー,或擁有最少4項綠技",
  "勝利のレシピ/勝利的食譜": "技能改動:1.中距離2.比賽終段前半=速+35001.擁有最少4項提升加速力技能,或擁有最少4項中距離限定技能",
  "仕込みは完璧": "技能改動:比賽中段回+750,限定中距離1.育成事件「「その時間は贈り物」」擇下方,或スタミナ600+2.勝出日本ダービー,或擁有最少2項中距離限定技能",
  "黒い閃光/黑色閃光": "速+3500→45001.育成事件「心に誇りを」成功,或ファン数150000+2.パワー800+",
  "完璧なエラー対処術/完美的錯誤對應術": "額外回+1501.スピード800+,或パワー800+2.擁有最少2項回復持久力技能",
  "甘さ控えめエスケープ": "逃げ+賢さ1200UP+比賽中段後半+前半名次=速+35001.曾發生育成事件「Apply」,或擁有最少3項提升速度技能2.以「逃げ」作戰及第1人氣勝出最少2場G1",
  "パーフェクトブート/完美啟動": "額外速+15001.育成事件「Missionforバレンタイング」成功,或ファン数150000+2.スタミナ600+",
  "メジロアルダン目白阿爾丹": "Danserleprésent",
  "永遠の輝き/永恆的光輝": "額外速+15001.出戰菊花賞,或擁有最少5項提升速度技能",
  "刹那への覚悟/奪下剎那的決心": "速+3500→45001.出戰第2年天皇賞,或擁有最少4項中距離限定技能",
  "アドマイヤベガ愛慕織姬": "CrystalMist",
  "静かな誓い/沉靜的誓言": "額外速+15001.勝出日本ダービー,或以追込作戰勝出最少2場重賞2.擁有最少3項提升速度技能",
  "己身焦がすほうき星/燃燒已身的彗星": "速+3500→45001.擁有最少2項追込限定技能2.パワー800+",
  "マチカネタンホイザ待兼唐懷瑟": "ごろりん！？パワードライブ滾呀滾！？強力迴旋",
  "どんっ、パッ、むんっ咚、啪、姆！": "比賽中段於中間位置時回復耐力及稍為提升速度1.比賽中段及後半路程2.第3至前名次=回+550,速+2500/繼承回+150,速+500",
  "ゴーイングマイウェイ/Goingmyway": "額外速+15001.曾發生育成事件「マチタンのむんむんデー」並成功,或擁有最少5項提升速度技能",
  "えい！えい！むん！/加油！加油！姆！": "額外回+1501.勝出最少2場長距離重賞,或スタミナ600+2.擁有最少2項長距離限定技能",
  "キタサンブラック北部玄駒": "ミンナノアタシへ！成為大家的我！",
  "祭りだワッショイ！/祭典來了嘿呀！": "加速力+4000→50001.曾發生育成事件「緊急開店！キタちゃんマッサージ」,或擁有最少2項逃げ限定技能2.スピード800+",
  "爆風一閃！": "速+3500→45001.有馬記念二連霸,或スタミナ600+2.擁有最少2項長距離限定技能",
  "サトノダイヤモンド里見光鑽": "ポンテ・デ・ディアマン鑽石鋒芒",
  "金剛不壊/金剛不壞": "額外速+15001.勝出最少3場G1,或スタミナ600+2.擁有最少3項提升速度技能",
  "隠せぬ輝き": "回+550→150,速+35001.曾發生育成事件「憧れを追いかけて」,或擁有最少2項差し限定技能2.擁有最少3項提升速度技能,或スピード800+",
  "右回りの輪舞曲/順時針的輪舞曲": "速+60,力+60→速+80,力+801.育成第2年勝出最少2場重賞2.擁有最少2項綠技",
  "メジロブライト目白光明": "Illuminateyou",
  "不屈のお嬢様/不屈的大小姐": "回+550→7501.勝出最少4場長距離比賽,或擁有最少4項回復持久力技能",
  "動かざること羊蹄山の若し/如羊蹄山般屹立不搖": "回+750→9501.擁有最少2項長距離限定技能2.スタミナ600+",
  "逃げろ~♪/快逃囉~♪": "額外回+1501.勝出皐月賞,或以逃げ作戰勝出最少3場G12.擁有最少2項回復持久力技能",
  "サプライズ大成功~": "速+3500→45001.擁有最少4項逃げ限定技能,或擁有最少5項提升速度技能",
  "レコードランナー/紀錄跑者": "額外回+1501.スピード800+,或根性600+2.擁有最少2項中距離限定技能,或擁有最少2項長距離限定技能",
  "圧巻のトリック/震撼全場的手法": "額外速+35001.賢さ800+2.パワー800+",
  "見惚れるコーナリング/令人著迷的過彎": "技能變更:最後彎位=速+45001.持有「愛嬌」狀態完成育成,或ファン数150000+2.擁有最少3項提升速度技能",
  "煌めきのトップスタァ/輝煌的頂尖巨星": "速+3500→45001.勝出高松宮記念、安田記念,或以先行作戰勝出兩場G12.擁有最少2項先行限定技能",
  "ニシノフラワー西野花": "FloweringDreams",
  "風花疾走/風花疾馳": "額外回+1501.勝出最少5場G1",
  "一輪の勇気/一朵的勇氣": "速+3500→45001.育成事件「夜に咲く想い」發生第3次2.擁有最少5項提升速度技能",
  "大輪の決意/盛開的決心": "加速力+3000→40001.スピード800+2.パワー800+",
  "ヤエノムテキ八重無敵": "剛勇果断、烈火之刀",
  "昂る焔/激昂之焰": "持續時間1.8秒→4秒1.育成事件「極限の修行」選擇上方並成功,或擁有最少5項提升速度技能",
  "八重の向こう意気/八重的鬥爭心": "速+3500→45001.勝出皐月賞、日本ダービー,或擁有最少4項中距離限定技能",
  "勝利に焦がれる激情": "中距離+比賽終段+最後彎位+有追越對象=現在速+35001.勝艸場中距離G1,或パワー800+2.根性600+",
  "頑張るしかないよね/只能加油了呢": "技能改動:1.差し2.比賽終段前半=速+35001.幹勁在好調或以上發生育成事件「草野球でエール！」,或曾與育成角色外出2.擁有最少3項提升速度技能",
  "ノンストップエール/不停頓聲援ノンストップガール": "額外回+1501.幹勁在好調或以上發生育成事件「草野球でエール！」,或曾與育成角色外出2.擁有最少2項提升加速力技能",
  "竜の雲を得る如し/蛟龍得水": "持續時間3秒→4秒1.幹勁在好調或以上發生育成事件「応援行脚」,或曾與育成角色外出2.擁有最少2項差し限定技能",
  "春風吹きて、桜舞う/春風吹拂,櫻花飛舞": "速+60,力+60→速+80,力+801.幹勁在好調或以上發生育成事件「応援行脚」,或曾與育成角色外出2.擁有最少2項綠技",
  "アイネスフウジン艾尼風神": "フレッシュパーラー清新待客",
  "じゃじゃウマお姉ちゃん/強悍賽馬娘的大姐姐": "額外速+15001.勝出日本ダービー,或以逃げ成戰勝出最少2場重賞2.擁有最少3項提升速度技能",
  "荒ぶる風神/狂野風神": "持續時間1.8秒→4秒1.根性600+2.擁有最少2項中距離限定技能",
  "メジロパーマー目白善信": "Jinglealltheway",
  "パないっしょ？/不得了吧？": "持續時間3秒→4秒1.持有技能「大逃げ」,或スピード800+2.擁有最少3項提升速度技能",
  "テンアゲスタイル": "技能變更:比賽中段+並排2秒,限定長距離=速+45001.勝出最少2場長距離G1,或擁有最少2項長距離限定技能2.根性600+",
  "神逃げの心得/神速領頭的心得": "持續時間3秒→4秒1.持有技能「大逃げ」,或スタミナ600+2.擁有最少2項長距離限定技能",
  "＃カレンに染まってみる？/#要染成真機伶的顏色嗎？": "額外速+15001.持有「愛嬌〇」狀態完成育成,或ファン数150000+2.擁有最少3項提升速度技能",
  "心奪われる閃光/令人神魂顛倒的閃光": "技能變更:比賽開始5秒後+比賽早後半+前半名次=速+35001.勝出最少3場短距離G12.擁有最少2項短距離限定技能",
  "＃ビューティースプリント/#漂亮短途賽": "額外速+15001.持有「切れ者」狀態完成育成,或スピード800+2.パワー800+,或賢さ800+",
  "思い出を力に変えて/將回憶化為力量": "速+3500→45001.勝出マイルCS,或賢さ800+2.擁有最少2項マイル限定技能",
  "モリガンの矛戟/戰鬥女神的矛戟": "額外視野+51.曾發生「MoreFun!」育成事件,或勝出最少2場G12.擁有最少2項提升加速力技能",
  "理想へ向かう覚悟": "發動技能後最後300m速+15001.擁有最少2項先行限定技能,或根性600+2.擁有最少3項提升速度技能",
  "イナリワン稻荷一": "灯穂燈穗",
  "火消の梯子登り/打火英雄的急登梯": "速+3500→45001.育成事件「怒涛の恩返しラッシュ」選擇最上方,或スタミナ600+2.勝出最少2場芝重賞,或勝出最少2場ダート重賞",
  "熟練の砂塵使い/熟練的沙塵能手": "回550→7501.パワー800+2.擁有最少2項回復持久力技能",
  "粋でいなせな達人技": "回550→350,速+3500→45001.中距離重賞2勝,或擁有最少3項提升速度技能2.擁有最少2項中距離限定技能,或スピード800+",
  "スイープトウショウ東商變革": "とっておきmaterialize",
  "放課後魔法少女": "額外速+15001.曾發生育成事件「「これがやりたい！」,或擁有最少5項提升速度技能",
  "チャームマジック/魅惑魔法": "額外現在速+15001.勝出桜花賞,或パワー800+2.勝出オークス,或擁有最少2項提升加速力技能",
  "サルビアスプレンデンス": "額外現在速+15001.勝出オークス,或スピード800+2.勝出安田記念,或賢さ800+",
  "もっと冒険してみたい！/我想要體會更多冒險！": "持續時間1.8秒→4秒1.曾與育成角色外出,或曾與友人卡或團體卡外出2.擁有最少2項差し限定技能",
  "自信持って踏み出": "技能變更:差し+比賽後半=現在速+45001.曾與育成角色外出,或曾與友人卡或團體卡外出2.擁有最少2項差し限定技能",
  "起死回生の一歩/起死回生的一步": "持續時間1.2秒→4秒1.以差し作戰勝出最少2場G1,或スピード800+2.賢さ800+",
  "アドベンチャーの先導者/Adventure的先驅者": "速+3500→45001.以先行作戰及第1人氣勝出最少4場マイル/一哩G1",
  "真剣勝負デス！/認真比試喔！": "額外視野+51.育成時曾與該馬娘外出,或曾與友人或團體外出2.パワー800+",
  "エアシャカール空中神宮": "...foundyou.",
  "アップリフティング/振奮精神": "額外回+1501.勝出日本ダービー,或賢さ800+2.擁有最少2項回復持久力的技能",
  "LoseMyself": "額外現在速+15001.勝出皐月賞,或擁有最少2項追込限定技能2.勝出菊花賞,或擁有最少2項提升加速力技能",
  "怒涛の出陣/怒濤般的出陣": "額外回+1501.勝出ジャパンC,或勝出兩場長距離重賞2.擁有最少2項回復持久力的技能",
  "日之本一のド根性/日之本第一的毅力日本一のウマ娘": "速+3500→45001.スピード800+2.ファン数150000+",
  "神秘体験！ゴルシワープ/神祕體驗！阿船空間跳躍": "技能持續時間3秒→4秒1.スピード564+或パワー564+2.スタミナ564+或根性564+",
  "イカ揚げ、いかがですか！？/來點炸魷魚如何！？": "技能持續時間2.4秒→4秒1.擁有最少4項追込限定技能,或擁有最少4項中距離限定技能2.賢さ564+",
  "高まってきたぜぇ！！": "速+3500→4500,限定長距離1.G15勝2.擁有最少4項長距離限定技能",
  "夏の名優/夏日的名演員": "持續時間2.4秒→4秒1.勝出最少2場長距離重賞,或在暑期進行1次休息2.スピード800+",
  "一意専心にリフレッシュ！/專心一意恢復精神！": "回750→9501.スタミナ600+,或在暑期進行1次休息2.擁有最少2項回復持久力技能",
  "バンブーメモリー青竹回憶": "奥義・常夏バーニング！！奧義．盛夏燃燒！！",
  "風紀の登龍門/紀律的登龍門": "額外加速力+20001.安田記念賽取得前2名,或パワー800+2.擁有最少2項提升加速力技能",
  "龍虎相搏": "技能改動:限定差し+マイル,最後彎位+追越對手=現在速+35001.スピード800+,或擁有最少2項マイル限定技能2.根性600+",
  "押忍ッ！気合十分ッス！/喝啊！氣勢十足！": "額外加速力+20001.擁有最少4項差し限定技能",
  "コパノリッキー小林歷奇": "五獣挙りて彩光奏づ",
  "コパッと開運！/小伶俐地開運！": "速+3500→45001.發生5次やる気上升的育成事件,或擁有最少4項ダート限定技能",
  "押龍脈の波濤/龍脈的波濤": "速++80→++1001.勝出最少4場ダートG1,或擁有最少4項綠技",
  "夢に向かって急上昇！/朝著夢想驟升！": "額外回+1501.育成事件「私のファーストライブ」成功,或ファン数150000+2.擁有最少2項ダート限定技能",
  "最高峰のステージに！/絕對的中央站位！": "速+3500→45001.擁有最少4項ダート限定技能,或擁有最少5項提升速度技能",
  "絶対的センター！": "加速力4000→50001.完成育成事件「ConnectLive~それから~」,或擁有最少2項提升加速力技能2.勝出川崎記念,或スピード800+",
  "見せつけてやる！/就讓你們見識一下！！": "持續時間2.4秒→4秒1.擁有最少2項追込限定技能2.擁有最少3項提升速度技能",
  "起死回生の出力/起死回生的輸出": "持續時間1.2秒→4秒1.勝出最少2場中距離G12.擁有最少2項提升加速力技能",
  "千万バリキ！！！/千萬衝勁！！！": "持續時間2.4秒→4秒1.擁有最少4項差し限定技能,或擁有最少5項提升速度技能",
  "きっと飛べる！/一定能翱翔！": "持續時間2.4秒→4秒1.勝艸出2場中距離重賞2.パワー800+",
  "ユキノビジン雪之美人": "いっぱいおあげんしぇ！請多多品嚐看看餒！",
  "憧れのシチーガール/夢想中的都市女孩": "持續時間3秒→4秒1.勝出桜花賞,或スピード800+2.勝出オークス,或ファン数150000+",
  "雪国仕込みの直滑/雪國鍛鍊出的直線滑下": "持續時間3秒→4秒1.根性600+2.擁有最少2項先行限定技能",
  "決意の根性娘": "發動技能後最後300m速+15001.以先行作戰勝出最少3場G12.擁有最少3項提升速度技能",
  "シーキングザパール採珠": "Oh!bento-magic",
  "世界を貫く至高の輝き/貫穿世界的至高光輝": "額外現在速+1500,短距離/マイル俱可發動1.勝出最少2場短距離G1,或勝出最少2場マイルG12.擁有最少2項提升加速力技能",
  "パール流ダンスバトル/採珠流舞蹈對決": "持續時間2.4秒→4秒,短距離/マイル俱可發動1.曾發生育成事件「五目の輝きをつかめ！」,或[賢さ800+2.擁有最少2項短距離限定技能,或擁有最少2項マイル限定技能",
  "ライバルがいるから！/因為有好勁敵！": "額外回+1501.擁有最少4項提升加速力技能",
  "心に灯す闘志": "發動後額外最後直路速+15001.育成事件「ドトウのパリピ屋敷！？」大成功2.擁有最少4項先行限定技能",
  "魂の導き手/靈魂的引導者": "額外速+15001.勝出2項G12.擁有最少3項提升速度技能",
  "超特急入稿！": "額外回+1501.育成事件「哀しき怪物・ヲタキョンシー！」成功結果,或擁有最少2項回復持久力技能2.スピード800+",
  "たぎってきたぁ~~っ！！/為尊復活──！！": "持續時間1.8秒→4秒,限定ダート1.擁有最少2項ダート限定技能,或擁有最少3項提升速度技能2.スタミナ600+",
  "尊みを求めてふっかーーつ！": "持續時間3秒→4秒1.勝出最少2場ダートG12.パワー800+,或根性600+",
  "アストンマーチャン奧斯頓真弓": "ふわもこアワー",
  "必勝のピッチアップ/必勝的步頻提升": "持續時間1.2秒→4秒1.育成事件「いろいろおいしいみたいです」選擇上方並成功,或擁有最少2項逃げ限定技能2.スピード800+",
  "記憶に刻む足取り/刻劃在記憶中的腳步": "額外加速力+20001.勝出最少5場G1,或擁有最少4項短距離限定技能",
  "ヤマニンゼファー山人西風": "BreezyTreat",
  "ウインドシアー/風切": "持續時間2.4秒→4秒1.勝出マイルCS,或擁有最少2項マイル限定技能2.スピード800+",
  "神渡し/迎神之風": "速+2500→35001.曾發生育成事件「そこが輝くとき」,或擁有最少2項先行限定技能2.賢さ800+",
  "天つ風/天風": "技能變更:比賽後半+第3名或以下=速+35001.以先行戢法勝出最少4場G1,或擁有最少3項提升速度技能2.根性600+",
  "先達に献ぐ祈りの頌/獻給先賢的祈願頌歌": "速+3500→45001.スピード800+2.擁有最少2項中距離限定技能",
  "さあ、ウチとやろうや！/來,跟我一起做吧！": "速+3500→45001.勝出8場重賞2.擁有最少3項提升速度技能",
  "ほな、行くで！": "持續時間1.8秒→4秒1.ファン数150000+2.根性600+",
  "扇ノ舞/扇舞": "速+3500→45001.育成事件「怒涛の恩返しラッシュ」選擇最上方,或スピード800+2.擁有最少2項長距離限定技能",
  "大見得切り/獨演舞姿": "額外視野+51.勝出天皇賞,或以追込作戰勝出最少3場G12.擁有最少2項追込限定技能",
  "韋駄天ノ襲脚": "追込→追込+長距離,額外最後直路現在速+15001.勝出最少2場長距離G1,或擁有最少2項提升加速力技能2.パワー800+,或賢さ800+",
  "ナカヤマフェスタ中山慶典": "運否、聖夜の星に賭ける",
  "乾坤一擲の大博打/孤注一擲的大賭徒": "速+4500→55001.育成事件「酔狂なお遊び」選擇上方並成功,或擁有最少3項提升速度技能2.スピード800+",
  "鉄火のギャンブラー/驍勇的賭徒": "機率スピード、パワー、根性+80→機率スピード、パワー、根性+1001.育成事件「酔狂なお遊び」選擇上方並成功,或擁有2個綠技2.賢さ800+",
  "ワンダーアキュート奇銳駿": "湯守の和心",
  "闘魂注入/注入鬥魂": "持續時間2.4秒→4秒1.育成事件「立ち向かうためにZ」選擇上方並成功,或擁有最少2項マイル限定技能2.根性600+",
  "いぶし銀の闘志": "限定マイル→限定ダート,速+3500→4500,回+1501.ファン数150000+,或擁有最少3項提升速度技能2.賢さ800+",
  "女神の砂浴び/女神的沙浴": "持續時間3秒→4秒1.勝出最少4場ダートG1,或擁有最少4項ダート限定技能",
  "ぶっ差してやるぜ！/看我超車！": "額外速+15001.G14勝",
  "最速のトップギア/最快的最高檔速": "速4500→55001.スピード800+2.擁有最少2項差し限定技能",
  "おてんば女王/淘氣女王": "回+550→7501.以逃げ作戰勝出最少3場G12.スピード800+",
  "緋色の光となって": "逃げ+長距離+比賽早段後半+前半名次=速=3500,發動後+最後衝刺=加速力+20001.勝出最少2場長距離G12.擁有最少2項長距離限定技能",
  "開かれる夢の扉/開啟的夢想之門": "速+4500→55001.6次在重賞取得前2名2.スピード800+",
  "ゼンノロブロイ荒漠英雄": "未知との遭遇、即ち物語",
  "英雄への道標/成為英雄的路標": "回+550→7501.持有「切れ者」狀態完成育成,或賢さ800+2.擁有最少2項回復持久力技能",
  "物語を紡ぐ者": "回+550→回+150,速+35001.擁有最少4項先行限定技能,或擁有最少5項提升速度技能",
  "光輝く剣/綻放光芒之劍": "速+3500→45001.育成第3年勝出4次G12.擁有最少4項中距離限定技能",
  "BLAZINGWOLF": "持續時間2.4秒→4秒1.育成事件「飢えた戦士たち」成功,或擁有最少3項提升速度的技能2.擁有最少2項先行限定技能,或擁有最少2項差し限定技能",
  "渇望する怪物/飢渴的怪物": "加速力+4000→50001.勝出最少3場長距離G12.擁有最少2項長距離限定技能,或擁有最少2項提升加速力技能",
  "未来へ飛び立ちましょう！/一起飛向未來吧！": "持續時間3秒→4秒1.育成事件「似てないところもあるけれど」大成功,或スピード800+2.擁有最少4項逃げ限定技能",
  "必勝の前口上！/必勝的開場白！": "加速力+4000→50001.勝出最少2場G1,或スタミナ600+2.擁有最少3項提升速度技能",
  "無我の境地/無我的境界": "回-200→回-501.有馬記念二連霸,或スタミナ600+2.擁有最少2項長距離限定技能",
  "明けぬ夜はない！/沒有不會拂曉的夜晚！": "額外速+15001.育成事件「年末恒例！感謝の大掃除」大成功,或擁有最少3項提升速度技能2.スピード800+",
  "ホッコータルマエ北幸樽前": "とびだせポッピングシェル",
  "苫小牧グルメで舌鼓！/用苫小牧美食大飽口福！": "額外速+15001.曾發生育成事件「タルマエの旅行演習」,或擁有最少2項先行限定技能2.スピード800+,或スピード800+",
  "観光大使の面目躍如！/觀光大使聲名大噪！": "速+3500→45001.勝出最少4場ダートG1,或擁有最少4項ダート限定技能",
  "ひた走れ！苫小牧の星": "發動技能後,最大最後衝刺時額外加速力+20001.ファン数150000+,或擁有最少2項提升加速力技能2.スタミナ600+",
  "ダイタクヘリオス大德太陽": "ノッてけ、マッシュアップ！",
  "マジ爆上げっしょ！/真的超嗨的啦！": "持續時間2.4秒→4秒1.育成事件「フルーツサンドパーリィDAY」成功,或擁有最少3項提升速度技能2.スピード800+,或パワー800+",
  "とりまやったれ~！/總之大鬧一場~！": "持續時間2.4秒→4秒1.以逃げ作戰勝出最少2場G1,或以先行作戰勝出最少2場G12.擁有最少2項マイル限定技能",
  "オーダーはバッチリ！/點餐內容完美掌握！": "全基礎+101.以逃げ戰法勝出最少3場重賞,或擁有最少4項逃げ限定技能",
  "麗なサーブ/華麗出餐": "額外加速力+20001.育成事件「感謝を込めて、晩餐を」成功,或ファン数150000+2.擁有最少2項提升加速度技能",
  "夢叶える決意を授けましょう/授予達成夢想的決心吧": "加速力3000→40001.育成事件「WhiteHeartbeat」成功,或ファン数150000+2.擁有最少2項先行限定技能",
  "至高の勝利を召し上がれ/請享用至高的勝利": "速3500→45001.勝出最少3場中距離G1,或擁有最少3項提升速度技能",
  "踏み出す勇気をご覧あれ": "持續時間2.4秒→4秒1.曾發生育成事件「グイグイ貴族大会」,或賢さ800+2.スピード800+",
  "シンコウウインディ新光風": "DingDongBoo",
  "全速前進なのだ！/全速前進啦！": "速3500→4500曾發生育成事件「いたずら大計画、決行なのだ！」,或勝出最少3場ダート重賞2.スピード800+",
  "いたずらマイスター/惡作劇大師": "速+60,力+60→速+80,力+801.パワー800+,或根性600+2.擁有最少2項綠技",
  "泥んこ魔王様": "ダート比賽「良」或「稍」=速+40,力+40;「重」或「不良」=速+40,力+40,全基礎+201.勝出フェブラリーS,或在「重」「不良」馬場狀態勝出重賞2.擁有最少2項ダート技能",
  "ミスターシービー千明代表": "爛然闊歩",
  "天翔る足取り/翱翔天際的步伐": "現在速3500→45001.勝出皐月賞、日本ダービー、菊花賞,或擁有最少2項提升加速力技能2.ファン数150000+",
  "弾む大地/震撼大地": "額外視野+51.擁有最少4項追込限定技能2.賢さ800+",
  "ツインターボ雙渦輪": "エンジン点火！引擎點火！",
  "エンジン全開！大噴射！引擎全開！大噴射！": "在比賽中段開始長期增加速度,但在比賽末段減速1.比賽路程2.第1名名次,與後方馬娘相距1身位或以上=速+1500,比賽終段後半現在速-繼承速+500,比賽終段後半現在速-500",
  "出力1000万%！！/1000萬%輸出！！": "速+4500→55001.育成事件「ターボエンジン限界突破！！」選擇上方,或スピード800+2.擁有「大逃げ」技能,或擁有最少2項逃げ限定技能",
  "ターボについてこーい！/跟上渦輪吧──！": "加速力+4000→50001.以逃げ作戰勝出最少3場重賞2.擁有最少2項提升加速力技能",
  "ダイイチルビー第一紅寶": "蒼炎",
  "華麗であれ/保持華麗": "速+3500→45001.育成事件「不得手など、許されない」選擇上方並成功,或パワー800+2.擁有最少2項差し限定技能3.擁有最少3項提升速度技能",
  "我が一族の玉条を胸に": "差し→短距離,移除對手減速效果,速+3500→現在速+4500,沒有出現掛かり時現在速+55001.訓練未曾失敗,或曾發生最少3次やる気上升事件2.賢さ800+",
  "常に最たる輝きを/時時刻刻綻放最耀眼的光芒": "額外前方馬娘現在速-15001.勝出最少2場短距離G1,或勝出最少2場マイルG12.擁有最少2項短距離限定技能,或擁有最少2項マイル限定技能",
  "シンボリクリスエス克莉斯耶絲象徵": "ImmortalWork",
  "質実剛健/質樸剛健": "額外條件:中山賽場時回-200→+1501.勝出第2,第3年天皇賞、有馬記念,或パワー800+2.擁有最少2項差し限定技能",
  "革命をもたらす威容/帶來革命的嚴肅容貌": "額外回+150,長距離→中距離或長距離1.育成事件「突撃！商店街セール」選擇中間並成功,或スタミナ600+2.擁有最少2項長距離限定技能,或擁有最少2項中距離限定技能3.擁有最少2項回復持久力技能",
  "桜華爛漫一直線/櫻花爛漫一直線": "速+3500→45001.擁有最少3項提升速度技能2.スピード800+",
  "負けたくない！/我不想輸！": "回+350→5501.以先行作戰勝出最少2場G1,或パワー800+2.擁有最少4項中距離限定技能",
  "美しき燐光/美麗的燐光": "額外速+15001.擁有最少2項回復持久力技能2.スタミナ600+",
  "幽玄の灯火": "回550→350,額外速+25001.育成訓練未曾牧敗,或賢さ800+2.擁有最少3項提升速度技能",
  "淡く儚い残照/稍縱即逝的餘暉": "速+3500→5500,回-2001.勝出日本ダービー、天皇賞,或擁有最少4項中距離限定技能2.擁有最少2項先行限定技能3.スピード800+",
  "サクラローレル櫻花桂冠": "春光・Bonappétit",
  "桜前線進行中！/櫻花前線行進中！": "速+3500→45001.勝出天皇賞,或スタミナ600+2.擁有最少2項差し限定技能",
  "花咲かせましょう！/開起一朵花吧！": "現在速+3500→45001.曾發生育成事件「その体には努力が宿っている」,或擁有最少3項提升速度技能2.スピード800+3.擁有最少2項長距離限定技能",
  "ネオユニヴァース新宇宙": "EncounterWithU",
  "銀河のその先へ、あなたと/與你一起奔向銀河的彼端": "速+3500→45001.勝出皐月賞、日本ダービー,或擁有最少2項中距離限定技能2.賢さ800+",
  "星の海を駆けて/馳騁星海": "持續時間2.4秒→4秒1.曾發生育成事件「星空のコネクト」,或擁有最少2項綠技2.スピード800+3.擁有最少3項提升速度技能",
  "猪突猛進！バクシンロード！/橫衝直撞！驀進之路！": "速+3500→45001.勝出第2,第3年スプリンターズS,或スピード800+2.パワー800+",
  "驀進！爆進！バクシーン！/驀進！爆進！驀進──！": "持續時間3秒→4秒1.發生3次提升やる気育成事件,或擁有最少2項短距離限定技能2.擁有最少3項提升速度技能",
  "ポジティブスマイル/正向樂觀的笑容": "回+550→7501.發生3次提升やる気育成事件,或擁有最少2項差し限定技能2.スタミナ600+",
  "大どんでんがえし/跌破眼鏡": "持續時間1.8秒→4秒1.勝出最少2場中距離重賞,或パワー800+2.擁有最少2項中距離限定技能",
  "やばしやばし！": "發動技能後額外最後300m速+15001.曾發生育成事件「服に福来たれ！」,或擁有最少3項提升速度技能2.スピード800+",
  "ヒシミラクル菱鑽奇寶": "Bangミラクるわせ！Bang大爆冷門的奇蹟！",
  "焦らず、気負わず/不焦急、不逞強": "回+550→7501.休息7次或以上,或擁有最少2項回復持久力技能2.スタミナ600+,或根性600+",
  "できる範囲で頑張ろ~！/蒐集我的小確幸": "回+550→150,額外速+35001.以「差し」作戰勝出最少4場長距離G1,或ファン数150000+2.スピード800+,或パワー800+",
  "ちょっといいこと、集めて": "速+2500→35001.育成事件「やります、やりますってば」選擇上方並成功,或擁有最少3項提升速度技能2.勝出菊花賞、天皇賞,或擁有最少2項差し限定技能",
  "タニノギムレット谷水琴蕾": "深淵のテルプシコラー",
  "嵐を呼ぶ破壊神/喚來暴風雨的破壞神": "速+3500→45001.育成事件「蛇とオレンジと星」選擇上方,或パワー800+2.擁有最少2項追込限定技能",
  "酔い痴れよ、世界/為我陶醉吧,世界": "スピード,パワー+60→801.勝出NHKマイルC、日本ダービー,或ファン数150000+2.擁有最少2項マイル限定技能,或擁有最少2項中距離限定技能",
  "祝福のフラワーガール/祝福的花童": "額外隊友速+15001.擁有最少3項提升速度技能,或賢さ800+2.擁有最少2項先行限定技能,或擁有最少2項差し限定技能",
  "ヴェール揺らす春疾風/輕撫面紗的春日疾風": "額外加速力+2000,限定短距離/マイル1.勝出桜花賞、スプリンターズS,或スピード800+2.擁有最少2項短距離限定技能,或擁有最少2項マイル限定技能",
  "末永く、寄り添う花": "防定マイル+下坡=速+3000,隊友速+15001.與育成角色外出,或與友人卡或團體卡外出2.ファン数150000+",
  "熱烈エンゲージ！/熱烈的約定！": "速+2500→35001.勝出阪神JF、エリザベス女王杯,或擁有最少2項追込限定技能2.スピード800+,或賢さ800+",
  "闘魂入刀！/鬥魂入刀！": "持續時間1.2秒→4秒,限定追込+中距離1.發生育成事件「アンタとワルツを」,或パワー800+2.擁有最少2項提升加速力技能",
  "誓いの一振り": "限定追込+中距離,取消無掛かり及保持後方名次要求1.曾發生事件「アンタとワルツを」,或パワー800+2.擁有最少2項提升加速力技能",
  "マーベラスサンデー美麗週日": "喝采ワンダードール！",
  "ワクワクマーベラスゾーン/雀躍無比美麗領域": "速+3500→45001.勝出大阪杯、宝塚記念,或擁有最少2項中距離限定技能2.擁有最少3項提升速度技能",
  "ギュンギュンのマーベラス": "持續時間2.4秒→4秒1.發生3次提升やる気的事件2.擁有最少2項差し限定技能",
  "進め！世界マーベラス計画/前進吧！世界美麗計畫": "額外現在速+15001.發生育成事件「マーベラスDEダンス♪」,或ファン数150000+2.パワー800+,或賢さ800+3.擁有最少3項提升加速力技能",
  "熱血進化ライディング！/熱血進化的騎乘！": "額外於最後200m速+15001.スピード800+,或擁有最少2項差し限定技能2.擁有最少2項提升加速力技能",
  "必殺！爆速スプリント！/必殺！爆快短途！": "額外於最後200m速+15001.擁有最少2項短距離限定技能,或擁有最少3項提升速度技能2.パワー800+3.根性600+",
  "ワンチャンまくったる！/抓準機會再拚一波囉！": "東京賽場時額外速+2500,非東京賽場無額外加成1.パワー800+,或擁有最少2項中距離限定技能2.スピード800+,或スタミナ600+",
  "あたししか勝たん！/贏家一定是我！": "東京賽場時額外加速力+2000,非東京賽場無額外加成1.擁有最少2項差し限定技能2.擁有最少3項提升速度技能3.擁有最少2項提升加速力技能",
  "あたしサイコーじゃん！": "限定差し+中距離,比賽終段前半+名次=現在速+4500,東京賽場=現在速+55001.曾發生育成事件「手に取る『かわいい』は少し重たくて」,或勝出最少2場東京賽場比賽2.與育成角色外出,或與友人卡或團體卡外出",
  "カツラギエース葛城榮主": "決意一筆",
  "してやったり！/我做到了！": "加速力+4000→50001.育成事件「ギャルの手も借りたい」成功,或擁有最少2項提升加速力技能2.スピード800+",
  "逃げっ切りの1人旅/領先到最後的單人旅行": "技能改動:比賽中段大幅領先,於最後直路速度上升),東京中距離賽時效果上升)1.擁有「大逃げ」技能,或擁有最少2項逃げ限定技能2.パワー800+,或根性600+",
  "シリウスシンボリ天狼星象徵": "駆るは光、狩るは星々",
  "一等星のアラベスク/一等星的華麗曲": "速+3500→45001.育成事件「シリウス先輩がすごい理由」成功,或擁有最少3項提升速度技能2.賢さ800+",
  "追想のトロイメライ": "速+3500→1500,回+5501.勝出最少3場中距離G1,或擁有最少2項回復持久力技能2.擁有最少3項提升速度的技能",
  "揺るがぬアスター/堅定無比的流星": "速+3500→45001.勝出日本ダービー,或擁有最少2項中距離限定技能2.パワー800+",
  "瑠璃色エスケイプ/琉璃色的逃脫": "速+3500→45001.已習得「大逃げ」,或擁有最少2項逃げ限定技能2.スピード800+3.スタミナ600+,或擁有最少3項提升速度技能",
  "滄海を超えしフーガ": "逃げ+2200m+比賽中段後半+第1名=速+45001.以「逃げ」戰法及第1人氣勝出6場重賞",
  "蒼天を駆けるラーファガ/奔馳於蒼天的陣風": "加速力+4000→50001.勝出最少2場中距離G12.擁有最少2項中距離限定技能,或擁有最少2項提升加速力技能",
  "ラプラスの悪魔/拉普拉斯的惡魔": "速+80→1001.擁有最少2項綠技2.擁有最少2項中距離限定技能,或パワー800+",
  "眩耀のルクシオン/眩曜的光子": "隨スピード數值額外x速+5001.勝出皐月賞,擁有最少2項先行限定技能2.擁有最少3項提升速度技能",
  "ナリタトップロード成田路": "JoytotheWorld",
  "ターフの主人公/草地的主角": "條件更新:提升パワー及スピード,バ場狀態為「良」時效果上升,限定草地。速,力+801.勝出菊花賞,或擁有最少2項綠技2.スピード800+3.パワー800+",
  "正道": "追加於最後衝刺時提升加速力)1.育成事件「勃発！委員長バトル！」點選上方,擁有最少3項提升速度技能2.擁有最少2項長距離限定技能",
  "押し寄せるジュテーム/排山倒海而來的愛意": "追加於最後直路時提升速度,速+15001.擁有最少2項提升加速力技能,或スピード800+2.擁有最少2項追込限定技能,或スタミナ600+",
  "荒磯好みの黄金船/喜愛驚濤密岩的黃金船": "速,力+60→80,同時增加漏閘問題1.於バ場状態在「稍重」「重」或「不良」勝出G1,或擁有最少2項綠技2.勝出兩次宝塚記念,或パワー800+",
  "蒼色革命": "持續時間1.8秒→4秒1.勝出最少2場中距離G1,或スピード800+2.擁有最少2項提升加速力技能",
  "ダンス・デ・レペ/劍舞": "速+3500→4500,ロンシャン賽場+絶好調時額外持續時間3秒→4秒1.與育成角色外出1次,或與友人或團體外出1次2.擁有最少2項中距離限定技能,或スタミナ600+",
  "ケイエスミラクル": "幸せの青い光幸福的藍光",
  "K.Speed": "短距離比賽:額外現在速+1500,非短距離無加成1.勝出最少4場短距離比賽,或擁有最少3項提升速度技能2.根性600+",
  "流れ星の軌跡": "限定先行→先行+マイル,持續時間1.8秒→4秒1.勝出最少4場マイルG12.擁有最少2項マイル限定技能",
  "命の火花/生命的煙火": "額外於最後200m時速+15001.育成事件「高架下の捜索」選擇上方,或擁有最少2項提升加速力技能2.スピード800+",
  "Gluttony’sGrip": "回+350→5501.擁有最少2項回復持久力技能,或スタミナ600+2.擁有最少2項長距離限定技能",
  "ノイズキャンセリング": "額外現在速+35001.持有「注目株」狀態完成育成,或ファン数150000+2.パワー800+",
  "刑苦": "持續時間3秒→4秒1.勝出最少2場長距離重賞,或賢さ800+2.擁有最少3項提升速度技能",
  "BurnDown": "速+3000,回+350,額外全隊友速+15001.擁有最少2項回復持久力技能,或スタミナ600+2.擁有最少3項提升速度技能",
  "Service:Transit": "持續時間1.8秒→4秒1.勝出最少3場中距離重賞,或スピード800+2.擁有最少2項提升加速力技能,或擁有最少2項差し限定技能",
  "メジロラモーヌ目白拉茉奴": "解けぬ結い目",
  "純愛": "現在速+3500→45001.G17勝或以上",
  "高嶺の艷笑/高嶺的豔笑": "持續時間2.4秒→4秒1.曾發生育成事件「この愛は、尽きることなく」,或擁有最少5項提升速度技能",
  "純天賦の身ごなし/天賦異稟的靈敏身手": "額外條件2500m比賽+耐1000=加速力+4000→5000+比賽終段前8路程隨機發動,非條件無加成1.勝出ジャパンC、有馬記念,或擁有最少2項提升加速力技能2.スピード800+",
  "盤楽遊嬉/放情遊樂": "比賽早段後半→比賽中段後半,回550→350,額外速+25001.育成事件「『シン』を射る」成功,或擁有最少3項提升速度技能2.スタミナ600+,或パワー800+",
  "朝腹、朝腹、かやすしや♪": "技能改動:比賽中段前半+前半名次=速+4500,回-1001.ファン数150000+,或擁有最少2項先行限定技能2.賢さ800+",
  "トップ・オブ・ザ・姫！": "速+4500→55001.勝出秋華賞、エリザベス女王杯,或擁有最少2項差し限定技能2.スピード800+",
  "最っっっ高のプリンセス": "差し+中距離+最後直路=現在速+3500,同時京都賽場時現在速+3500→55001.スタミナ600+2.擁有最少2項中距離限定技能",
  "爆走猛姫✩急転直下！！": "額外條件:マイル或中距離,額外加速力+20001.育成事件「舞い姫、奉りて」成功,或擁有最少3項提升速度技能2.根性600+,或パワー800+",
  "タップダンスシチー踢踏城市": "RomanticHorizon",
  "BreakawayStar！": "速+3500→45001.習得「大逃げ」技能,或擁有最少2項逃げ限定技能2.スピード800+",
  "SmoothSailing!": "速+3500→4500,額外條件第1名名次1.ファン数150000+,或擁有最少3項提升速度技能2.根性600+,或パワー800+",
  "北風一蹴": "持續時間3秒→4秒1.長距離重賞2勝,或擁有最少2項長距離限定技能2.スピード800+",
  "メリクリ↑パーリー": "額外條件:大逃げ+長距離,速3500→4500,中山賽場+絶好調時回350→5501.有馬記念二連霸,或擁有最少2項回復持久力技能2.スタミナ600+",
  "聖夜の天路": "效果變更:現在速+25001.擁有最少4項差し限定技能",
  "雪華の追い上げ": "效果變更:現在速+35001.長距離重賞3勝,或スタミナ600+2.擁有最少3項提升速度技能",
  "サトノクラウン里見皇冠": "夏雷カスケード！",
  "アンビシャスカード": "速+3500→45001.育成事件「バックステージ・マジック」選取上或中間選項並成功,或ファン数150000+2.擁有最少2項差し限定技能,或擁有最少3項提升速度技能",
  "ミリオンカード": "2400m路程比賽時回-200,加速力4000→5000,以外距離無此額外效果1.擁有最少2項中距離限定技能,或擁有最少2項提升加速力技能2.パワー800+,或根性600+",
  "シュヴァルグラン高尚駿逸": "Tidebreaker",
  "偉大なる踏破": "條件變更:先行+中距離+比賽後半+前半名次=速+2500,加速力+3000,額外2400m或以上=速+3500,加速力+30001.G13勝,或擁有最少4項中距離限定技能",
  "全力投球": "速+3500→45001.曾發生育成事件「たまにはおやつも」,或擁有最少3項提升速度技能2.ファン数150000+,或根性600+",
  "あっぱれ！臥竜勇往/吉兆驚天！臥龍勇往": "發動技能後,額外最後直路現在速+15001.曾發生育成事件「スポットライトを、きみに」,或スピード800+2.擁有最少2項長距離限定技能",
  "万里飛び越えソイヤッ！/飛越萬里嘿呀！": "發動技能後,額外最後直路現在速+15001.有馬記念二連霸,或擁有最少2項逃げ限定技能2.擁有最少2項提升加速力技能",
  "いい味、出てるでしょ？/味道有出來了對吧？": "速+3500→45001.曾發生育成事件「ネイチャ先生の盛り上げ講座」,或擁有最少2項提升速度技能2.スピード800+",
  "大掃除上手/大掃除高手": "持續時1.8秒→4秒1.以差し作戰勝出最少2場中距離重賞,或擁有最少2項提升加速力技能2.パワー800+,或賢さ800+",
  "盛り上げ上手": "差し+中距離+比賽終段前4+或之後名次=加速力+2000,現在速+25001.勝出最少2場G1,或ファン数150000+2.擁有最少2項中距離限定技能,或擁有最少2項差し限定技能",
  "ヴィブロス強擊": "デラックスファウンテン",
  "天来のリトルシスター": "額外條件マイル/中距離,額外加速力+20001.勝出最少3場G1,或擁有最少3項提升速度技能2.擁有最少2項マイル限定技能,或擁有最少2項中距離限定技能",
  "ハイソ・メンタリティ！": "持續時2.4秒→4秒1.與育成角色外出,或與友人卡或團體卡外出2.パワー800+,或賢さ800+",
  "迫りくる宵闇": "發動技能後額外最後直路速+15001.擁有最少2項追込限定技能,或擁有最少3項提升速度技能2.パワー800+",
  "玄界領域": "現在速+3500→45001.以追込戰法勝出最少2場長距離重賞,或スタミナ600+2.擁有最少2項長距離限定技能",
  "もうひとけっぱり！": "速+3500→45001.以先行戰法勝出最少4場重賞2.擁有最少2項先行限定技能",
  "曲線に舞う深雪": "額外速+15001.曾發生育成事件「秘密のれっすん！」,或擁有最少3項提升速度技能2.パワー800+",
  "下弦の雪月花": "彎位→最後彎位,芝/草地賽時持續時間3秒→4秒1.擁有最少2項提升加速力技能,或擁有最少2項マイル限定技能2.スピード800+",
  "ビコーペガサス微光飛駒": "ペガサスフルパワー！",
  "疾風爆走ペガサスダッシュ！": "比賽後半或之後於後方曾追越對手,剩餘150m於前方時速度上升比賽路程或之後+或之後名次+追越對手1.最後150m2.前半名次=速+4500/繼承速+2500",
  "急行！ヒーロー参上！": "速+3500→45001.達成育成事件「ターフの上のヒーロー」目標,或擁有最少5項提升速度技能",
  "必殺・雷電キーック！": "額外加速力+20001.勝出最少4場短距離重賞,或擁有最少3項短距離限定技能2.スピード800+,或パワー800+",
  "イクノディクタス生野狄杜斯": "千歳、廻りて",
  "百錬成鋼": "比賽中保持冷靜,最後衝刺時速度上升1.沒有出現掛かり2.最後衝刺=速+2500/繼承速+500",
  "徹底管理プラン": "回550→750,腳質先行→先行或差し1.訓練未曾失敗,或重賞3勝或以上2.擁有最少2項回復持久力技能,或賢さ800+",
  "鉄火花": "速+4500→5500,腳質差し→先行或差し1.勝出オールカマー,或擁有最少3項提升速度技能2.擁有最少2項先行限定技能,或擁有最少2項差し限定技能",
  "ドゥラメンテ大鳴大放": "羅刹、赤翼にて天上へ至らん",
  "磨穿鉄硯": "速+2500→35001.育成事件「鍛錬の先へ」為育實訓練效果,或擁有最少3項提升速度技能2.スピード800+,或パワー800+",
  "赫焉": "增加附合條件:中山賽場的比賽終段的彎位;額外最後直路速+15001.G16勝+",
  "トランセンド創昇": "Info:Acquired",
  "情報強者": "マイル或中距離賽=加速力+4000→5000,非條件無加成1.G13勝+,或擁有最少2項提升加速力技能2.賢さ800+",
  "『未知』を求めて": "速+3500→45001.育成事件「かっこいい情報屋さん？」成功,或擁有最少2項ダート限定技能2.與育成角色外出,或與友人卡或團體卡外出",
  "ラインクラフト萊茵實力": "ずっとずっと輝いて",
  "未来を拓け！": "速+3500→45001.育成事件「ぽかぽかのお誘い」選擇上方並成功,或擁有最少3項提升速度技能2.與育成角色外出,或與友人卡或團體卡外出3.パワー800+,或根性600+",
  "やってみせるんだ！！": "先行+マイル+最後彎位+前半名次=速+2500,東京賽場額外速+25001.擁有最少2項マイル限定技能2.ファン数150000+",
  "ぜーったい負けられない！": "發動技能後額外最後直路速+15001.G14勝,或擁有最少4項先行限定技能",
  "霹靂閃電": "限定變更:マイル+差,增加可發動條件:比賽終段前半1.勝出最少2場マイルG1,或擁有最少2項提升加速力技能2.賢さ800+",
  "灰と化すまで": "速+2500→3500,持續時間2.4秒→4秒1.擁有最少4項マイル限定技能,或擁有最少5項提升速度技能",
  "トレンド先取り": "加速力+4000→50001.根性600+,或ファン数150000+2.擁有最少2項逃げ限定技能",
  "マイル神、爆✩誕": "速+3500→45001.マイルCS二連霸,或擁有最少5項提升速度技能",
  "全・力・ワク・ワク！！": "東京+2400m=速+3500→4500,非條件無加成1.勝出日本ダービー,或スピード800+2.擁有最少2項中距離限定技能",
  "Dreamer'sPath": "速+2500→35001.以差し作戰勝出最少3場G1,或擁有最少5項提升速度技能",
  "サウンズオブアース萬籟爭鳴": "ケ・ピアチェーヴォレ！",
  "カエスーラ": "額外速+15001.曾發生育成事件「どこでもメロディーア！」,或ファン数150000+2.スタミナ600+,或根性600+",
  "トライアンフ": "速+3500→45001.擁有最少2項差し限定技能,或擁有最少3項提升速度技能2.パワー800+",
  "エスプロズィオーネ": "差し+長距離+比賽中段後半=速+3500,回-3001.賢さ800+2.ファン数150000+",
  "流水流走": "速+3500→45001.擁有最少3項提升速度技能2.スピード800+",
  "神仙蝶変の術": "距離4身位內條件→距離6身位內1.以「先行」作戰勝出最少4場長距離G12.擁有最少4項先行限定技能",
  "将の疾刃": "額外衝刺速+15001.以「先行」作戰勝出最少2場G1,或以「差し」作戰勝出最少2場G12.パワー800+",
  "無双の追撃": "額外條件:內側賽道時速3500→4500,非條件無加成1.擁有最少4項先行限定技能,或擁有最少4項差し限定技能",
  "光速を超える粒子": "非中距離速3500→4500,中距離速3500→50001.以「先行」作戰勝出最少3場中距離G1,或擁有最少4項先行限定技能",
  "被験体観察": "額外條件:2000m比賽時額外隊友速+1500,非條件無加成1.擁有最少4項提升速度技能2.スピード800+,或パワー800+",
  "ノースフライト北方飛翔": "ShiningRunway",
  "ココロ、キラめくままに！": "持續時間1.8秒→4秒,賢さ1200以上時額外速3500→40001.ファン数150000+,或擁有最少3項提升速度技能2.賢さ800+",
  "EnjoytheFlight": "發動技能後額外最後200m速+15001.勝出最少3場マイルG1,或擁有最少2項提升加速力技能2.擁有最少2項マイル限定技能,或スピード800+",
  "遮るものはない": "マイル→短距離/マイル1.擁有最少2項短距離限定技能,或擁有最少2項マイル限定技能2.パワー800+",
  "不屈の証明": "短距離→短距離/マイル1.曾發生育成事件「タコさんの足は増えたり減ったり」,或擁有最少3項提升速度技能2.賢さ800+",
  "一流の在り方": "持續時間2.4秒→4秒1.勝出最少4場g12.根性600+",
  "シルフィード・マギア": "2200m比賽時加速力+4000→5000,非條件無加成1.以「追込」作戰勝出最少4場中距離G1,或擁有最少2項提升加速力技能2.スピード800+",
  "ノクス・ルミナ": "追込+中距離+比賽終段前4=加速力+3000,同時2000m比賽時額外現在速+2500,回-2001.根性600+2.擁有最少2項中距離限定技能",
  "緊急魔力ブースト": "發動技能後額外比賽終段最後直路速+15001.擁有最少2項追込限定技能,或擁有最少3項提升速度技能2.パワー800+",
  "ジャングルポケット森林寶穴": "FaithintheFeral",
  "猛襲の牙": "持續時間2.4→4秒,パワー1200或以上時速+3500→40001.擁有最少3項提升速度技能2.パワー800+3.スタミナ600+",
  "闘叫の鬼": "條件改動:中距離+東京賽場+比賽中段前半=現在速+3500,加速力+10001.育成事件「憧れに託されて」大成功,或勝出日本ダービー2.持有「切れ者」狀態完成育成,或スピード800+",
  "天上天下唯我爆走": "條件改動:中距離+比賽中段前半=現在速+45001.勝出最少4場中距離G1,或擁有最少4項中距離限定技能",
  "ドリームジャーニー夢之旅": "夢寐に見る銀世界",
  "果てへの面舵": "速、力+60→801.育成事件「同じ釜のお茶漬け」選擇上方,或擁有最少2項綠技2.パワー800+,或賢さ800+",
  "夢見心地": "現在速+2500→3500,中山賽場及賢さ1200+時現在速+2500→40001.勝出最少4場G1",
  "山頂でイタダキマス": "條件增加比賽後半路程1.擁有最少2項先行限定技能,或擁有最少2項提升加速力技能2.根性600+",
  "淀の祝福": "耐、賢+60→801.勝出最少2場都賽場比賽,或スタミナ600+",
  "カルストンライトオ浮岩光王": "無二無三なる一条の路",
  "閃光一走！": "技能改動:出閘時加速力上升=加速力+1000,後於直路向前推進=現在速+3500,限定逃げ+短距離1.勝出最少5場短距離賽,或擁有5項短距離限定技能",
  "突風一駆！": "技能改動:出閘時加速力上升=加速力+1000,後於直路向前推進=現在速+3500,限定逃げ+短距離1.曾發生育成事件「今でも変わらないもの」,或擁有最少2項逃げ限定技能2.擁有最少3項提升速度技能,或スピード800+",
  "RittervonFuchu": "耐、賢、速+60→801.3勝東京賽場比賽2.賢さ800+",
  "閃光の奔流": "東京賽場時回+150,非東京賽場回-3001.擁有最少2項差し限定技能,或擁有最少3項提升速度技能2.根性600+",
  "感謝のふるさとメドレー": "第1段速+2500→4500,第2段現在速+2500→加速力+20001.ファン数150000+,或擁有最少3項提升速度技能2.スピード800+",
  "突き進め北の海": "取消名次要求,不足1800m比賽終段前半路程發動,1800m或以上比賽終段前4路程發動1.曾發生育成事件「夢見るワンデイトリップ」,或擁有最少3項提升加速力技能2.賢さ600+",
  "ジェンティルドンナ貴婦人": "烈華の洗礼",
  "――お退きなさい": "技能變更:先行+2000m或以上+比賽終段前4路程+前方有對手保持接近距離1秒=加速力+4000,轉換跑線+2501.G18勝或以上2.持有「切れ者」狀態完成育成,或パワー800+",
  "PowerAmI": "速+3500→45001.擁有最少2項中距離限定技能,或擁有最少2項先行限定技能2.スピード800+,或スタミナ600+",
  "淑女の独壇場": "先行+2500m+比賽中段後半發動=パワー1200或以上時速+5500,不足時速+45001.育成事件「”力”と矜持」成功,或擁有最少5項提升速度技能",
  "勇躍閃々": "速+3500→45001.以「先行」作戰勝出最少4場G1,或擁有最少3項提升速度技能2.賢さ800+",
  "嵐纏いし英雄は往く": "限定秋→秋或冬,速,力+60→801.スピード800+,或パワー800+2.擁有最少2項綠技",
  "ルミナス・スペクトラム": "額外同隊員現在速+15001.曾發生育成事件「スリープ・コンパートメントメイト」,或賢さ800+2.根性600+",
  "METIレゾナンス": "限定芝→芝+中距離,速+60→1001.勝出最少2場中距離G1,或パワー800+2.擁有最少2項綠技",
  "シーザリオ西沙里奧": "時かけるせせらぎ",
  "礎たれ": "持續時間3秒→4秒1.擁有最少3項提升速度技能2.パワー800+,或賢さ800+",
  "一張一弛": "現在速+4500→55001.勝出オークス,或勝出最少3場中距離G12.擁有最少2項中距離限定技能",
  "デュランダル多旺達": "Lamedevent",
  "忠心のヴェイヤンティフ": "速+4500→5500,回-200→-3001.擁有最少4項追込限定技能,或擁有最少5項提升速度技能",
  "オリファントの轟雷": "取消名次要求；發動技能處於彎位時加速力4000→5000,非條件無加成1.擁有最少2項短距離限定技能,或擁有最少2項マイル限定技能2.スピード800+,或パワー800+",
  "お先にテールウィンド": "同條件+領先時回-200,持續時間0.9秒→1.8秒,非領先無加成1.擁有最少2項長距離限定技能,或擁有最少2項提升加速力技能2.スピード800+",
  "コックピット・マジシャン": "發動技能後額外最後直路現在速+15001.擁有最少2項逃げ限定技能,或擁有最少2項提升速度技能2.スタミナ600+",
  "ミストラルに乗って": "限定短距離或マイル,非東京賽場時直路→比賽終段+直路,東京賽場時直路→比賽終段前半+直路1.勝出最少2場短距離G1,或勝出最少2場マイルG12.パワー800+",
  "海の底からキラめいて…": "限定短距離或マイル,發動時處於最後彎位時速+2500→4500,非最後彎位無加成1.擁有最少2項短距離限定技能,或擁有最少2項マイル限定技能2.スピード800+",
  "バブルガムフェロー吹波糖": "暁霞を拓き、朝を掴む",
  "俊傑の悠": "條件1:先行+3路程=速+1500;條件2:先行+マイル或中距離+3路程+與領先2身位內=速+35001.勝出最少4場G1,或擁有最少2項先行限定技能2.パワー800+",
  "嚆矢の花道": "條件1:先行+最後200m=速+2500;條件2:先行+マイル或中距離+最後直路+與領先1身位內=現在速+55001.育成事件「ウマウマカワイイお菓子作り」選擇上方,或ファン数150000+2.根性600+",
  "シミュレートグラス・オン": "加速力+4000→6000,回-2001.擁有最少2項先行限定技能,或擁有2個長距離限定技能2.パワー800+",
  "ネオンの尾を引いて": "比賽中段前半=回+550,發動後比賽中段後半=速+25001.曾發生育成事件「君と至る最適解」,或勝出最少2場長距離G12.スタミナ600+",
  "ゼロレイテンシ": "持續時間2.4秒→4秒1.賢さ800+2.擁有最少3項提升速度技能",
  "不撓のLimitBreaker": "速+4500→55001.以「追込」作戰勝出最少3場G12.パワー800+",
  "エアメサイア": "辿る血脈、芽吹く未来",
  "母の面影を追って": "速3500→4500;賢さ1200+時速3500→50001.勝出最少5場G1,或擁有最少5項提升速度技能",
  "堅実なる秘策": "發動技能後額外於比賽後半下坡時速+15001.曾發生育成事件「休養グッズ検証会」,或擁有最少2項差し限定技能2.パワー800+,或賢さ800+",
  "ひたむきサンタクロース": "限定長距離+先行→限定先行1.擁有最少2項先行限定技能,或擁有最少2項回復持久力技能2.スタミナ600+",
  "暗い夜道もお任せを！": "持續時間2.4秒→4秒,回-200→-4001.以「先行」作戰勝出最少2場G1,或擁有最少3項提升速度技能2.パワー800+",
  "アル・ワーキを追いかけて": "限定中距離→限定中距離+追込,速3500→4500,2400m比賽時持續時間3秒→4秒1.以「追込」作戰+第1人氣勝出最少2場G12.スピード800+",
  "氷星融解": "限定中距離→限定中距離+追込,免除比賽早段速-1500效果,2400m比賽時持續時間2.4秒→4秒1.擁有最少2項中距離限定技能,或擁有最少3項提升速度技能2.パワー800+",
  "ウインバリアシオン凱旋芭蕾": "鋭気のアレグロ",
  "グラン・ジュッテ": "速+3500→45001.勝出最少2場G12.パワー800+,或根性600+",
  "邁進アン・レール": "發動技能後額外最後直路現在速+15001.完成育成事件「つい、くるりと」,或ファン数150000+2.スピード800+",
  "射貫く蒼": "速+4500→5500,回-200→-300;中山賽場+長距離時速+4500→6000,回-200→-01.擁有最少2項差し限定技能,或擁有最少3項提升速度技能2.根性600+",
  "勝機到来": "現在速+2500→35001.有馬記念二連霸,或勝出最少2場中距離G12.擁有最少2項中距離限定技能,或擁有最少2項長距離限定技能",
  "奪目の宙返り": "取消名次要求;同條件中於比賽後半有追越對手時持續時間3秒→4秒1.勝出皐月賞、日本ダービー、菊花賞,或ファン数150000+2.擁有最少3項提升速度技能",
  "さァさ、お立ち会い！": "取消名次要求,前名次無加成,之後名次加速力4000→50001.擁有最少2項追込限定技能,或擁有最少2項長距離限定技能2.パワー800+",
  "伏竜は目覚めて": "額外現在速+35001.勝出最少4場中距離G1,或ファン数150000+2.擁有最少2項提升加速力技能",
  "暁光背負いて": "現在速+3500→45001.擁有最少3項逃げ限定技能,或擁有最少3項中距離限定技能2.スピード800+",
  "天女の羽衣": "逃げ+マイル+比賽開始5秒後+有追後或被追越目標1秒=現在速+45001.曾發生育成事件「みんな前を向いて」,或スピード800+2.擁有最少2項逃げ限定技能,或擁有最少2項マイル限定技能",
  "神薙ダンス": "逃げ→逃げ+マイル,速+3500→現在速+45001.以「逃げ」作戰勝出最少2場マイルG12.パワー800+",
  "フリオーソ": "『船橋最強！』",
  "潮風の導き": "ダート比賽時持續時間2.4秒→4秒1.勝出最少4場ダートG1,或擁有3項ダート限定技能",
  "勇船直往": "現在速+3500→45001.擁有最少2項逃げ限定技能,或擁有最少2項先行限定技能2.スピード800+,或根性800+",
  "辻映りの妙技": "額外比賽開始時加速力+2000,發動後同時沒有「出遅れ」始能發動原上位技1.擁有最少2項短距離限定技能2.スピード800+",
  "覚えていてくださいね？": "比賽終段前4→比賽終段前81.擁有最少2項提升加速力技能2.パワー800+",
  "塵旋風となりて": "速+2500→35001.擁有最少2項先行限定技能,或擁有最少3項提升速度技能2.根性600+",
  "シルフ・スピリット": "先行→先行+マイル,距離領先馬娘2身位內→距離領先馬娘4身位內1.以「先行」作戰及第1人氣勝出最少2場G12.パワー800+",
  "ツルマルツヨシ鶴丸強志": "心、強し！",
  "燃え盛るは絶対の意志": "速+3500→現在速+3500,回+1501.勝出最少4場重賞,或擁有最少2項中距離限定技能2.根性600+",
  "千辛万苦切り裂く刃": "速+3500→45001.訓練未曾失敗,或擁有2先行限定技能2.パワー600+",
  "オルフェーヴル黃金巨匠": "我が覇道、阻むものなし",
  "我が意、即ち天の理なり": "條件變更:芝+追込+2000m或以上+最後衝刺=加速力+40001.勝出8場G12.スピード800+,或擁有最少2項追込限定技能",
  "王威絢爛": "技能發動後額外比賽中段後半速+25001.擁有最少4項中距離限定技能,或擁有最少5項提升速度技能",
  "――畏れよ、然して拝跪せよ": "速+3500→4500,回+150→3501.曾發生育成事件「王が労うは……」,或スタミナ600+2.持有「切れ者」狀態完成育成,或パワー800+",
  "グランアレグリア放聲歡呼": "¡Quéalegría!",
  "推してまいる！！": "マイル比賽時現在速+3500→4500,短距離比賽無加成1.勝出最少5場マイルG1,或擁有最少4項マイル限定技能",
  "万哩へ響け大歓声": "情況1:芝+マイル+比賽終段前4+或之後名次=現在速+5000,回-200情況2:芝+非マイル+比賽終段前半+或之後名次=現在速+4000,回-2001.曾發生育成事件「嬉しい気持ちは何マイル？」,或擁有最少2項提升加速力技能2.パワー800+3.根性800+",
  "ノーリーズン莫名其妙": "知宵欺敵、百戦不殆",
  "侵掠如火": "速+3500→45001.擁有最少4項中距離限定技能",
  "天下分け目": "差し+比賽後半=現在速+45001.勝出皐月賞,或賢さ800+2.擁有最少2項差し限定技能,或擁有最少3項提升速度技能",
  "TrueWire-to-Wire!": "速+4500→55001.以「逃げ」戰法勝出最少5場G12.擁有最少5項提升速度技能",
  "大航海、飄々と": "中距離比賽時額外現在速+1500,非中距離無加成1.持有技能「大逃げ」,或擁有最少4項中距離限定技能",
  "アレスの進撃": "額外比賽早段後半現在速-15001.パワー800+2.擁有最少2項マイル限定技能",
  "アルテミスの矢": "持續時間3秒→4秒,マイル比賽時速+3500→現在速+35001.以「追込」作戰勝出最少6場G1",
  "悪路のほうが好みでね": "賽場狀態「良」=速+60,力+60;「稍重」「重」「不良」=速+80,力+801.以賽場狀態「稍重」或「重」或「不良」勝出G1,或パワー800+2.根性600+",
  "BeattheStars": "賽場狀態「稍重」或「重」或「不良」時額外加速力+1000,賽場狀態「良」無加成1.擁有最少2項中距離限定技能2.擁有最少2項先行限定技能,或擁有最少2項差し限定技能",
  "フェノーメノ超常駿驥": "対象捕捉！正義遂行！",
  "あんぱんと牛乳": "回+550→750,長距離賽時額外速+15001.擁有最少4項長距離限定技能",
  "猛き獣は太陽に吼える": "額外最後直路速+1500,限定3200m或以上比賽1.擁有最少2項先行限定技能,或擁有最少3項提升速度技能2.スタミナ600+,或根性600+",
  "立ち位置ゼロ番！": "額外加速力+20001.勝出最少6場ダートG1,或ファン数150000+2.パワー800+",
  "爆レスあげちゃう": "第1段速+2500→3500,第2段額外加速力+10001.擁有最少2項先行限定技能,或擁有最少3項提升速度技能2.スタミナ600+,或根性600+",
  "黄龍、天へと昇る": "速+3500→45001.發生最少3次提升やる気的育成事件,或擁有最少3項提升速度技能2.根性600+",
  "走る縁起物": "交流重賞時速+80,力+80,非交流重賞無加成1.曾發生育成事件「西日に黄金」,或勝出最少3場ダートG1",
  "ヴィルシーナ極峰": "Queen’sRebirth",
  "不撓不屈の女王": "マイル比賽時額外最後直路現在速+2500,回-200;非マイル比賽無加成1.育成事件「描くべき姿を」選擇上方,或擁有最少2項マイル限定技能2.根性600+",
  "お姉ちゃん、だもの": "マイル比賽時加速力4000→5000;非マイル比賽無加成1.勝出最少4場G1,或ファン数150000+2.パワー800+",
  "ラヴズオンリーユー唯獨愛你": "CirculatingLove♡",
  "ストリーミング♡ラッシュ": "速+2500→35001.擁有最少3項差し限定技能,或擁有最少2項中距離限定技能2.根性600+",
  "応援コメントよろしく！": "持續時間3秒→4秒;賢1200+時現在速+3500→40001.曾發生育成事件「緊急配信『次の企画どうする？』」,或ファン数150000+2.スタミナ600+",
  "LimitlessLove": "速+3500→45001.曾發生育成事件「Roommate」,或擁有最少3項先行限定技能2.パワー800+",
  "祝宴の征服者": "限定マイル→マイル或中距離,持續時間3秒→4秒成1.擁有最少2項マイル限定技能,擁有最少2項中距離限定技能2.賢さ800+",
  "栄華の歩み、誰ぞ遮る": "距離領先馬娘4身位或以內條件→無需此要求1.以「先行」作戰勝出最少4場G1,或擁有最少5項提升速度技能",
  "白妙の約定": "速+3500→45001.曾發生育成事件「花束をあなたに」,或擁有最少2項中距離限定技能2.パワー800+,或根性600+",
  "クロノジェネシス時代創世": "WeavingHistory",
  "永永無窮": "無名次限制,發動固有時持續時間2.4秒→4.8秒,非條件無加成1.擁有最少3項先行限定技能,或擁有最少3項提升速度技能2.スピード800+,或スタミナ600+",
  "夢の舞台へ": "差し+パワー1200++比賽中段=現在速+4500;同時或之後名次=現在速+55001.曾發生育成事件「思い出コーディネート！」,或曾發生最少3次やる気上升的育成事件2.擁有最少3項提升速度技能",
  "WildRunway": "速+4500→5500,發動技能位於名次時不用消耗耐力1.以「差し」作戰勝出最少2場G1,或擁有最少2項差し限定技能2.根性600+",
  "アイネスフウジン艾尼斯風神": "全力全開！サイクロン",
  "一番眺めのいい場所へ！": "加速力+4000→5000,無限定→限定中距離1.曾發生育成事件「貴方のクラスのお姉ちゃん」,或擁有最少4項中距離限定技能",
  "青空の下で待ってるよ！": "中距離比賽時額外速+1500,非條件無加成1.勝出日本ダービー,或擁有最少3項提升速度技能2.根性600+",
  "フサイチパンドラ火神": "ホップステップ・ゲッチュ♡",
  "ラブミーパレード": "速+3500→4500,2200m比賽時+3500→55001.曾發生育成事件「あと1枚？もう1枚！」,或擁有最少3項提升速度技能2.與育成角色外出,或與友人卡或團體卡外出3.スタミナ600+,或根性600+",
  "ぜーったい譲って♡": "加速力+4000→5000;2200m比賽時加速力+4000→5000,比賽終段前4→8,回-2001.勝出最少5場G12.擁有最少4項中距離限定技能",
  "希望は巡る、何度でも": "現在速+3500→4500,回+150→3501.勝出桜花賞、オークス、秋華賞2.スピード800+",
  "ティアラ・ダイブ！": "加速力+3000→40001.曾發生事件「夢の紡ぎ」,或擁有最少3項先行限定技能2.パワー800+",
  "煌めきのイリュージョン": "先行/差し→差し+中距離,持續時間2.4秒→4秒1.擁有最少3項差し限定技能,或パワー800+2.根性600+",
  "波上のラストトリック": "速+3500→4500,賢さ1200+時速+3500→55001.曾發生事件「重ねて、紡いで」,或擁有最少3項提升速度技能2.勝出最少4場G1,或擁有最少2項中距離限定技能",
  "マリンブルー・ライナー": "先行→先行+長距離,速+2500→35001.勝出最2場長距離比賽,或擁有2個長距離限定技能2.根性600+",
  "いつもの僕じゃないから！": "先行→先行+長距離,加速力+4000→5000,額外現在速+15001.持有「切れ者」狀態完成育成,或擁有最少2項先行限定技能2.スタミナ600+",
  "ヴィブロス比布魯斯": "ジュ・テームバカンス！",
  "デザートジュエルに魅せられ": "速+3500→45001.曾發生事件「あの頃みたいに」2.スピード800+",
  "いざ征かん！マリンロード": "速+2500→3500,京都賽場及賢さ1200+時速+2500→40001.勝出秋華賞,或擁有最少2項差し限定技能2.賢さ800+",
  "スティルインラブ愛如往昔": "スカーレットリリィの高揚",
  "赫き胎動": "速+3500→5500,需曾發動技能「衝動」1.勝出最少6場G12.パワー800+",
  "誰にも告げぬ誓い": "第1段:中距離+比賽中段+上坡=現在速+4500,第2段:已發動第1段+曾發「衝動」+比賽或之後+下坡=現在速+25001.擁有最少4項中距離限定技能,或擁有最少5項提升速度技能",
  "呼び覚まされし願い": "第2段:比賽終段→比賽終段前4=現在速+2500→3500,需曾發動技能「衝動」1.曾發生育成事件「ハチャメチャ大競技大会！」,或根性600+2.曾與育成角色外出,或曾與友人/團體支援卡外出",
  "ケイエスミラクル喜嘉奇蹟": "きせき・おもい・かなで",
  "『見ていて、くださいね』": "短距離=速+4500→5500,無回消耗,非短距離無加成1.以「先行」作戰勝出最少4場G1,或擁有最少2項先行限定技能2.スピード800+",
  "彗星色の羽搏き": "額外全隊友現在速+15001.曾發生育成事件「優しいまなざし」,或擁有最少2項短距離限定技能2.パワー800+",
  "ヒシミラクル菱奇蹟": "小さな奇跡、フォーユー♪",
  "お邪魔しま～す♪": "速+3500→45001.曾發生育成事件「癒しのミラクルオアシス」,或擁有最少3項提升速度技能2.パワー800+",
  "まさかここから大逆転！？": "差し+中距離+比賽終段前8+或之後名次=加速力+3000,下坡+最大最後衝刺=額外現在速+45001.勝出最少2場中距離G12.擁有最少2項差し限定技能,或擁有最少2項中距離限定技能",
  "エスポワールシチー希望城市": "PunkishBite",
  "ベッコベコに凹ます！": "1800m或以下路程時比賽終段前半→比賽終段前4,1801m或以上路程無加成1.勝出最少4場ダートG12.パワー800+",
  "相手が誰でも関係ねーし！": "速+3500→4000,回+350→-2001.根性600+2.擁有最少3項提升速度技能",
  "ビリーヴ信念": "念い、信ずればこそ",
  "無極": "持續時間2.4秒→4秒1.根性600+2.擁有最少2項提升速度技能",
  "徹骨徹髄": "短距離→先行+短距離,速2500→35001.パワー800+,或賢さ800+2.擁有最少2項短距離限定技能",
  "煌めきドーリィステージ": "中距離→差し+2000m或以上,天氣晴れ=現在速+3500→5500,非晴れ無加成1.曾發生育成事件「癒し目覚めろ、マーベラスポット巡り」,或パワー800+2.スタミナ600+",
  "いざ、ショーベラスタイム♪": "バ場状態「良」賢さ、スピード+60→賢さ、スピード+100,非「良」無加成1.擁有最少2項中距離限定技能,或擁有最少2項長距離限定技能2.擁有最少2項綠技",
  "手招きシュガーランタン": "速+3500→45001.パワー800+2.擁有最少2項短距離限定技能,或擁有最少2項マイル限定技能",
  "満たせぱんぷきんパワー！": "短距離或マイル時加速力+4000→5000,非條件無加成1.曾發生育成事件「ちっちゃなボーノのおっきな心」,或擁有最少2項先行限定技能2.以「先行」作戰勝出最少4場G1",
  "乗っとけぶち上げペース": "速+2500→3500,距離領先4位以上時速+2500→40001.勝出最少2場中距離重賞,或勝出最少2場長距離重賞2.スタミナ600+",
  "ここ、カマしどきっしょ！": "條件1:先行或差し+2499m+比賽終段+最後彎位=加速力+5000條件2:先行或差し+長距離+比賽終段+最後彎位=現在速+25001.パワー800+2.擁有最少2項先行限定技能,或擁有最少2項差し限定技能",
  "ダンツフレーム緞通烈焰": "照らすのはわたしの焔",
  "わたしだって、勝ちたい！！！": "中距離→先行,中距離比賽時發動技能後有追い比べ時額外現在速+25001.根性600+2.擁有最少2項先行限定技能,或擁有最少3項提升速度技能",
  "IgnitethisStage": "中距離比賽時額外加速力+20001.曾發生育成事件「心を込めたひとときを」,或スタミナ600+2.曾與育成角色外出,或曾與友人卡或團體卡外出",
  "トランセンド創升": "地熱解放オーヴァードライブ",
  "勝ち筋ドミネーション": "無限定→限定マイル或中距離,發動技能後及沒有出遅れ時額外於最後衝刺加速力+10001.賢さ600+2.擁有最少2項マイル限定技能,或擁有最少2項中距離限定技能",
  "ここ、逃す手はないってね": "發技能後對手馬娘有發動速度技能時自身額外現在速+15001.持有「切れ者」狀態完成育成,或パワー800+2.勝出最少3場ダートG1",
  "大地轟く大噴湯": "現在速+3500→45001.勝出最少3場G12.パワー800+",
  "風まかせ、お湯まかせ": "速+3500→4500,根性1200+時速+3500→5500,額外限定ダート1.根性600+2.擁有最少2項先行限定技能,或擁有最少2項差し限定技能",
  "ブエナビスタ迷人景致": "ToOurVista",
  "ふたりの約束、とどく時": "追込+中距離→追込+2500m,根幹距離時現在速+3500→4500,非根幹無加成1.パワー800+,或賢さ800+2.擁有最少2項追込限定技能",
  "誠心たる光燿": "追込+中距離→追込+芝+マイル/中距離,技能發動位置:比賽終段前半;比賽終段+最後彎位1.勝出最少6場G1",
  "一点張りでいこう": "中距離+於比賽終段追越對手時額外速+15001.パワー800+,或擁有最少2項差し限定技能2.根性600+",
  "勝負師の才略": "中距離→中距離/長距離,比賽終段前半→比賽終段前4,現在速+4500→55001.勝出最少3場G12.擁有最少3項中距離限定技能,或擁有最少2項長距離限定技能",
  "雪暗れに微笑む": "比賽終段前半→比賽終段前4,賢さ1200+時現在速+3500→40001.勝出最少2場長距離G12.擁有最少2項追込限定技能,或擁有最少2項長距離限定技能",
  "さて、収めに参りましょう": "追込→追込+長距離,全隊員額外速+15001.育成事件「マイ･ディア･リコレクション」選擇下方「飾り付け、俺も手伝っていいかな？」並成功,或スタミナ600+2.スピード800+",
  "尽きぬ炎": "先行→マイル或長距離,發動技能後及有發動追い比べ時於最後200m額外速+25001.持有「切れ者」狀態完成育成,或根性600+2.擁有最少2項マイル限定技能,或擁有最少2項長距離限定技能",
  "天地を揺らせ君の名で": "先行+中山芝2500m+進入比賽終段=加速力+4000,比賽路程於第1名或與領先馬娘距離4身位以內時加速力+4000→50001.有馬記念二連霸,或以「先行」作戰勝出最少3場G12.スピード800+",
  "灰の怪物": "先行+マイル+進入比賽終段=加速力+5000,進入比賽終段第1名或與領先馬娘距離4身位以內時加速力+5000→60001.曾發生育成事件「また、走り出す」,或パワー800+2.擁有最少2項提升加速力技能",
  "ステイゴールド黃金旅程": "黄金を訪ねて",
  "見果てぬ旅路": "無限定→差し,速+3500→4500,最大最後衝刺時→絶好調時速+4500→6500,回-2001.勝出最少3場G12.根性600+,或擁有最少2項差し限定技能",
  "針が交わる時": "差し+中距離+進入比賽終段=現在速+2500,發動後+最終彎位+有追越目標+最後400m+名次=速+35001.擁有最少2項中距離限定技能2.擁有最少3項提升速度技能",
  "旅の心得": "差し+長距離+比賽後半+直路+名次=速+2500,發動後+最後1000m=現在速+15001.曾發生育成事件「遊び心とかくれんぼ」,或スタミナ800+2.擁有最少2項長距離限定技能",
  "梅仰ぎ、漕ぐ計略": "速,力+60→全基礎+601.勝出最少2場マイルG1,或勝出最少2場中距離G12.パワー800+",
  "春道踏破": "中距離比賽時速+3500→50001.根性600+2.擁有最少2項先行限定技能",
  "初空高く、花宴": "速,耐+60→801.勝出最少2場中距離G1,或勝出最少2場長距離G12.スタミナ800+",
  "春めき、Lumière": "先行或差し→差し+長距離,速+3500→4500,發動後於最後衝刺前半速=15001.根性600+2.擁有最少2項差し限定技能,或擁有最少2項長距離限定技能",
  "風上に立て": "マイル→マイル或中距離,追越對手→第1名或追越對手,發動技能後東京賽場時額外比賽終段的最後直路現在速+25001.擁有最少2項マイル限定技能,或擁有最少2項中距離限定技能2.パワー800+",
  "ハジける風雲児": "マイル或中距離比賽時發動技能後於最後直路現在速=15001.曾發生事件「似た者同士のパトロール」,或根性600+2.以先行作戰勝出最少4場G1",
  "キセキ神業": "想像×創造＝∞",
  "ブラッシュアップ！": "差し→逃げ,無名次要求。「大逃げ」效果變更為速+2500,回+3501.スピード800+2.擁有最少3項提升速度技能",
  "緊急重版": "差し+長距離→逃げ+2000m或以上比賽,中後名次→前半名次。前2名額外現在速+25001.根性600+2.擁有最少2項提升加速力技能",
  "飛び出せSheepy!": "マイル比賽時速+2500→4500,回-200,非マイル比賽無加成1.根性600+2.擁有最少2項先行限定技能,或擁有最少3項提升速度技能",
  "SheepStampede!": "先行+マイル+比賽終段前8+領先或追對手=加速力+40001.持有「切れ者」狀態完成育成,或パワー800+2.勝出最少3場マイルG1",
  "ムジカ・シンティッランテ": "額外隊友及自己速+15001.曾發生育成事件「生活にムジカを！」,或スタミナ600+2.パワー800+",
  "ドーノ・ディ・フローラ！": "中距離時隊友及自己速+1500,非中距離無加成1.以「先行」作戰勝出最少2場G12.擁有最少2項先行限定技能,或擁有最少3項提升速度技能",
  "ロイスアンドロイス萊斯萊斯": "アピール宣言！",
  "絶対最強アピール宣言": "比賽中段於前方與其他馬娘並排時較短時間內速度上升,其後有追い比べ時較短時間內稍為向前推進第1段:1.比賽中段2.前半名次3.與其他馬娘並排2秒=速+3500//繼承速+1500第2段:1.已發動第1段2.有追い比べ=現在速+1500/繼承現在速+350",
  "巧みなるファントム": "先行+中距離+比賽後半彎位+轉換跑線=加速力+3000,現在速+15001.賢さ800+2.擁有最少2項中距離限定技能",
  "認知度、急上昇！": "速+3500→45001.パワー800+2.擁有最少3項提升速度技能"
}